Workbook
Name ACTION: #REF!

Sheet Cover
B2: TEST REPORT DOCUMENT
B4: An Adaptive VSTEP Preparation System | E4: Creator | F4: Hoàng Văn Anh Nghĩa
B5: SP26SE145 | F5: 46150
B6: SP26SE145_001_v1.2 | F6: 1.2
A10: Effective Date | B10: Version | C10: Change Item | D10: *A,D,M | E10: Change description | F10: Reference
A11: 46150 | B11: 1.1 | C11: New document | D11: A | E11: Create VSTEP test report
A12: 46172 | B12: 1.2 | C12: Final | D12: M | E12: Filter to 215 cases, match repository implementation

Sheet Test Cases
D1: TEST CASE LIST
B3: Project Name | D3: An Adaptive VSTEP Preparation System
B4: Project Code | D4: SP26SE145
B5: Test Environment Setup Description | D5: 1. Backend-v2 API + PostgreSQL 2. Frontend-v3 learner web 3. Admin web app 4. Mobile-v2 app 5. AI grading + SSE + wallet/payment
B8: No | C8: Function Name | D8: Sheet Name | E8: Description | F8: Pre-Condition
B9: 1 | C9: Register | D9: Register | E9: Register learner with email, onboarding data | F9: Valid Guest account/data exists
B10: 2 | C10: Login | D10: Login | E10: Login with email/password, session, redirect | F10: Valid Learner account/data exists
B11: 3 | C11: Google Login | D11: Google Auth | E11: Google Sign-In integration | F11: Valid Learner account/data exists
B12: 4 | C12: Session & Refresh | D12: Session | E12: Token refresh, logout, lifecycle | F12: Valid Learner account/data exists
B13: 5 | C13: Profile CRUD | D13: Profile | E13: List, create, switch, update, onboarding | F13: Valid Learner account/data exists
B14: 6 | C14: Vocabulary & SRS | D14: Vocabulary | E14: Topic list, detail, exercises, SRS review | F14: Valid Learner account/data exists
B15: 7 | C15: Grammar Points | D15: Grammar | E15: Point list, detail, exercise flow | F15: Valid Learner account/data exists
B16: 8 | C16: Listening Practice | D16: Listening | E16: Exercise list, audio, answer, results | F16: Valid Learner account/data exists
B17: 9 | C17: Reading Practice | D17: Reading | E17: Exercise list, passage, questions, results | F17: Valid Learner account/data exists
B18: 10 | C18: Writing Practice | D18: Writing | E18: Prompt, editor, submit, AI feedback, SSE | F18: Valid Learner account/data exists
B19: 11 | C19: Speaking Drills | D19: Speaking Drills | E19: Pronunciation drill, recording, feedback | F19: Valid Learner account/data exists
B20: 12 | C20: VSTEP Speaking | D20: VSTEP Speaking | E20: VSTEP session, submit, grading | F20: Valid Learner account/data exists
... B45: 37 | C45: Non-functional | D45: Non-functional | E45: Security, performance, compatibility, usability, reliability | F45: Valid System account/data exists

Sheet Test Statistics
B1: TEST STATISTICS
B3: Project Name | C3: An Adaptive VSTEP Preparation System | E3: Creator | H3: Hoàng Văn Anh Nghĩa
B4: Project Code | C4: SP26SE145 | E4: Reviewer/Approver | H4: Hoàng Văn Anh Nghĩa
B5: Document Code | C5: =C4&"_"&"001"&"_"&"v1.0" | E5: Issue Date | H5: 46150
B6: Notes
B10: No | C10: Module code | D10: Passed | E10: Failed | F10: Pending | G10: N/A | H10: Number of test cases
B11: 1 | C11: =Register!B2 | D11: =COUNTIF(Register!$F$12:$F$997,"Passed") | E11: =COUNTIF(Register!$F$12:$F$997,"Failed") | F11: =COUNTIF(Register!$F$12:$F$997,"Pending") | G11: =COUNTIF(Register!$F$12:$F$997,"N/A") | H11: =Register!B4
B12: 2 | C12: =Login!B2 | D12: =COUNTIF(Login!$F$12:$F$997,"Passed") | E12: =COUNTIF(Login!$F$12:$F$997,"Failed") | F12: =COUNTIF(Login!$F$12:$F$997,"Pending") | G12: =COUNTIF(Login!$F$12:$F$997,"N/A") | H12: =Login!B4
B13: 3 | C13: ='Google Auth'!B2 | D13: =COUNTIF('Google Auth'!$F$12:$F$997,"Passed") | E13: =COUNTIF('Google Auth'!$F$12:$F$997,"Failed") | F13: =COUNTIF('Google Auth'!$F$12:$F$997,"Pending") | G13: =COUNTIF('Google Auth'!$F$12:$F$997,"N/A") | H13: ='Google Auth'!B4
B14: 4 | C14: =Session!B2 | D14: =COUNTIF(Session!$F$12:$F$997,"Passed") | E14: =COUNTIF(Session!$F$12:$F$997,"Failed") | F14: =COUNTIF(Session!$F$12:$F$997,"Pending") | G14: =COUNTIF(Session!$F$12:$F$997,"N/A") | H14: =Session!B4
B15: 5 | C15: =Profile!B2 | D15: =COUNTIF(Profile!$F$12:$F$997,"Passed") | E15: =COUNTIF(Profile!$F$12:$F$997,"Failed") | F15: =COUNTIF(Profile!$F$12:$F$997,"Pending") | G15: =COUNTIF(Profile!$F$12:$F$997,"N/A") | H15: =Profile!B4
B16: 6 | C16: =Vocabulary!B2 | D16: =COUNTIF(Vocabulary!$F$12:$F$997,"Passed") | E16: =COUNTIF(Vocabulary!$F$12:$F$997,"Failed") | F16: =COUNTIF(Vocabulary!$F$12:$F$997,"Pending") | G16: =COUNTIF(Vocabulary!$F$12:$F$997,"N/A") | H16: =Vocabulary!B4
B17: 7 | C17: =Grammar!B2 | D17: =COUNTIF(Grammar!$F$12:$F$997,"Passed") | E17: =COUNTIF(Grammar!$F$12:$F$997,"Failed") | F17: =COUNTIF(Grammar!$F$12:$F$997,"Pending") | G17: =COUNTIF(Grammar!$F$12:$F$997,"N/A") | H17: =Grammar!B4
B18: 8 | C18: =Listening!B2 | D18: =COUNTIF(Listening!$F$12:$F$997,"Passed") | E18: =COUNTIF(Listening!$F$12:$F$997,"Failed") | F18: =COUNTIF(Listening!$F$12:$F$997,"Pending") | G18: =COUNTIF(Listening!$F$12:$F$997,"N/A") | H18: =Listening!B4
B19: 9 | C19: =Reading!B2 | D19: =COUNTIF(Reading!$F$12:$F$997,"Passed") | E19: =COUNTIF(Reading!$F$12:$F$997,"Failed") | F19: =COUNTIF(Reading!$F$12:$F$997,"Pending") | G19: =COUNTIF(Reading!$F$12:$F$997,"N/A") | H19: =Reading!B4
B20: 10 | C20: =Writing!B2 | D20: =COUNTIF(Writing!$F$12:$F$997,"Passed") | E20: =COUNTIF(Writing!$F$12:$F$997,"Failed") | F20: =COUNTIF(Writing!$F$12:$F$997,"Pending") | G20: =COUNTIF(Writing!$F$12:$F$997,"N/A") | H20: =Writing!B4
B21: 11 | C21: ='Speaking Drills'!B2 | D21: =COUNTIF('Speaking Drills'!$F$12:$F$997,"Passed") | E21: =COUNTIF('Speaking Drills'!$F$12:$F$997,"Failed") | F21: =COUNTIF('Speaking Drills'!$F$12:$F$997,"Pending") | G21: =COUNTIF('Speaking Drills'!$F$12:$F$997,"N/A") | H21: ='Speaking Drills'!B4
B22: 12 | C22: ='VSTEP Speaking'!B2 | D22: =COUNTIF('VSTEP Speaking'!$F$12:$F$997,"Passed") | E22: =COUNTIF('VSTEP Speaking'!$F$12:$F$997,"Failed") | F22: =COUNTIF('VSTEP Speaking'!$F$12:$F$997,"Pending") | G22: =COUNTIF('VSTEP Speaking'!$F$12:$F$997,"N/A") | H22: ='VSTEP Speaking'!B4
B23: 13 | C23: ='Conversation AI'!B2 | D23: =COUNTIF('Conversation AI'!$F$12:$F$997,"Passed") | E23: =COUNTIF('Conversation AI'!$F$12:$F$997,"Failed") | F23: =COUNTIF('Conversation AI'!$F$12:$F$997,"Pending") | G23: =COUNTIF('Conversation AI'!$F$12:$F$997,"N/A") | H23: ='Conversation AI'!B4
B24: 14 | C24: =Shadowing!B2 | D24: =COUNTIF(Shadowing!$F$12:$F$997,"Passed") | E24: =COUNTIF(Shadowing!$F$12:$F$997,"Failed") | F24: =COUNTIF(Shadowing!$F$12:$F$997,"Pending") | G24: =COUNTIF(Shadowing!$F$12:$F$997,"N/A") | H24: =Shadowing!B4
B25: 15 | C25: ='Exam Library'!B2 | D25: =COUNTIF('Exam Library'!$F$12:$F$997,"Passed") | E25: =COUNTIF('Exam Library'!$F$12:$F$997,"Failed") | F25: =COUNTIF('Exam Library'!$F$12:$F$997,"Pending") | G25: =COUNTIF('Exam Library'!$F$12:$F$997,"N/A") | H25: ='Exam Library'!B4
B26: 16 | C26: ='Exam Start'!B2 | D26: =COUNTIF('Exam Start'!$F$12:$F$997,"Passed") | E26: =COUNTIF('Exam Start'!$F$12:$F$997,"Failed") | F26: =COUNTIF('Exam Start'!$F$12:$F$997,"Pending") | G26: =COUNTIF('Exam Start'!$F$12:$F$997,"N/A") | H26: ='Exam Start'!B4
B27: 17 | C27: ='Exam Draft'!B2 | D27: =COUNTIF('Exam Draft'!$F$12:$F$997,"Passed") | E27: =COUNTIF('Exam Draft'!$F$12:$F$997,"Failed") | F27: =COUNTIF('Exam Draft'!$F$12:$F$997,"Pending") | G27: =COUNTIF('Exam Draft'!$F$12:$F$997,"N/A") | H27: ='Exam Draft'!B4
B28: 18 | C28: ='Exam Panels'!B2 | D28: =COUNTIF('Exam Panels'!$F$12:$F$997,"Passed") | E28: =COUNTIF('Exam Panels'!$F$12:$F$997,"Failed") | F28: =COUNTIF('Exam Panels'!$F$12:$F$997,"Pending") | G28: =COUNTIF('Exam Panels'!$F$12:$F$997,"N/A") | H28: ='Exam Panels'!B4
B29: 19 | C29: ='Exam Submit'!B2 | D29: =COUNTIF('Exam Submit'!$F$12:$F$997,"Passed") | E29: =COUNTIF('Exam Submit'!$F$12:$F$997,"Failed") | F29: =COUNTIF('Exam Submit'!$F$12:$F$997,"Pending") | G29: =COUNTIF('Exam Submit'!$F$12:$F$997,"N/A") | H29: ='Exam Submit'!B4
B30: 20 | C30: ='Exam Result'!B2 | D30: =COUNTIF('Exam Result'!$F$12:$F$997,"Passed") | E30: =COUNTIF('Exam Result'!$F$12:$F$997,"Failed") | F30: =COUNTIF('Exam Result'!$F$12:$F$997,"Pending") | G30: =COUNTIF('Exam Result'!$F$12:$F$997,"N/A") | H30: ='Exam Result'!B4
B31: 21 | C31: ='Wallet Balance'!B2 | D31: =COUNTIF('Wallet Balance'!$F$12:$F$997,"Passed") | E31: =COUNTIF('Wallet Balance'!$F$12:$F$997,"Failed") | F31: =COUNTIF('Wallet Balance'!$F$12:$F$997,"Pending") | G31: =COUNTIF('Wallet Balance'!$F$12:$F$997,"N/A") | H31: ='Wallet Balance'!B4
B32: 22 | C32: ='Top-up'!B2 | D32: =COUNTIF('Top-up'!$F$12:$F$997,"Passed") | E32: =COUNTIF('Top-up'!$F$12:$F$997,"Failed") | F32: =COUNTIF('Top-up'!$F$12:$F$997,"Pending") | G32: =COUNTIF('Top-up'!$F$12:$F$997,"N/A") | H32: ='Top-up'!B4
B33: 23 | C33: ='Promo Redeem'!B2 | D33: =COUNTIF('Promo Redeem'!$F$12:$F$997,"Passed") | E33: =COUNTIF('Promo Redeem'!$F$12:$F$997,"Failed") | F33: =COUNTIF('Promo Redeem'!$F$12:$F$997,"Pending") | G33: =COUNTIF('Promo Redeem'!$F$12:$F$997,"N/A") | H33: ='Promo Redeem'!B4
B34: 24 | C34: =Dashboard!B2 | D34: =COUNTIF(Dashboard!$F$12:$F$997,"Passed") | E34: =COUNTIF(Dashboard!$F$12:$F$997,"Failed") | F34: =COUNTIF(Dashboard!$F$12:$F$997,"Pending") | G34: =COUNTIF(Dashboard!$F$12:$F$997,"N/A") | H34: =Dashboard!B4
B35: 25 | C35: ='Course Enroll'!B2 | D35: =COUNTIF('Course Enroll'!$F$12:$F$997,"Passed") | E35: =COUNTIF('Course Enroll'!$F$12:$F$997,"Failed") | F35: =COUNTIF('Course Enroll'!$F$12:$F$997,"Pending") | G35: =COUNTIF('Course Enroll'!$F$12:$F$997,"N/A") | H35: ='Course Enroll'!B4
B36: 26 | C36: =Booking!B2 | D36: =COUNTIF(Booking!$F$12:$F$997,"Passed") | E36: =COUNTIF(Booking!$F$12:$F$997,"Failed") | F36: =COUNTIF(Booking!$F$12:$F$997,"Pending") | G36: =COUNTIF(Booking!$F$12:$F$997,"N/A") | H36: =Booking!B4
B37: 27 | C37: ='Admin Dashboard'!B2 | D37: =COUNTIF('Admin Dashboard'!$F$12:$F$997,"Passed") | E37: =COUNTIF('Admin Dashboard'!$F$12:$F$997,"Failed") | F37: =COUNTIF('Admin Dashboard'!$F$12:$F$997,"Pending") | G37: =COUNTIF('Admin Dashboard'!$F$12:$F$997,"N/A") | H37: ='Admin Dashboard'!B4
B38: 28 | C38: ='Admin Vocab Grammar'!B2 | D38: =COUNTIF('Admin Vocab Grammar'!$F$12:$F$997,"Passed") | E38: =COUNTIF('Admin Vocab Grammar'!$F$12:$F$997,"Failed") | F38: =COUNTIF('Admin Vocab Grammar'!$F$12:$F$997,"Pending") | G38: =COUNTIF('Admin Vocab Grammar'!$F$12:$F$997,"N/A") | H38: ='Admin Vocab Grammar'!B4
B39: 29 | C39: ='Admin Settings'!B2 | D39: =COUNTIF('Admin Settings'!$F$12:$F$997,"Passed") | E39: =COUNTIF('Admin Settings'!$F$12:$F$997,"Failed") | F39: =COUNTIF('Admin Settings'!$F$12:$F$997,"Pending") | G39: =COUNTIF('Admin Settings'!$F$12:$F$997,"N/A") | H39: ='Admin Settings'!B4
B40: 30 | C40: ='Admin Exams'!B2 | D40: =COUNTIF('Admin Exams'!$F$12:$F$997,"Passed") | E40: =COUNTIF('Admin Exams'!$F$12:$F$997,"Failed") | F40: =COUNTIF('Admin Exams'!$F$12:$F$997,"Pending") | G40: =COUNTIF('Admin Exams'!$F$12:$F$997,"N/A") | H40: ='Admin Exams'!B4
B41: 31 | C41: ='Admin Practice'!B2 | D41: =COUNTIF('Admin Practice'!$F$12:$F$997,"Passed") | E41: =COUNTIF('Admin Practice'!$F$12:$F$997,"Failed") | F41: =COUNTIF('Admin Practice'!$F$12:$F$997,"Pending") | G41: =COUNTIF('Admin Practice'!$F$12:$F$997,"N/A") | H41: ='Admin Practice'!B4
B42: 32 | C42: ='Admin Users'!B2 | D42: =COUNTIF('Admin Users'!$F$12:$F$997,"Passed") | E42: =COUNTIF('Admin Users'!$F$12:$F$997,"Failed") | F42: =COUNTIF('Admin Users'!$F$12:$F$997,"Pending") | G42: =COUNTIF('Admin Users'!$F$12:$F$997,"N/A") | H42: ='Admin Users'!B4
B43: 33 | C43: ='Admin Courses'!B2 | D43: =COUNTIF('Admin Courses'!$F$12:$F$997,"Passed") | E43: =COUNTIF('Admin Courses'!$F$12:$F$997,"Failed") | F43: =COUNTIF('Admin Courses'!$F$12:$F$997,"Pending") | G43: =COUNTIF('Admin Courses'!$F$12:$F$997,"N/A") | H43: ='Admin Courses'!B4
B44: 34 | C44: =Teacher!B2 | D44: =COUNTIF(Teacher!$F$12:$F$997,"Passed") | E44: =COUNTIF(Teacher!$F$12:$F$997,"Failed") | F44: =COUNTIF(Teacher!$F$12:$F$997,"Pending") | G44: =COUNTIF(Teacher!$F$12:$F$997,"N/A") | H44: =Teacher!B4
B45: 35 | C45: ='Grading AI'!B2 | D45: =COUNTIF('Grading AI'!$F$12:$F$997,"Passed") | E45: =COUNTIF('Grading AI'!$F$12:$F$997,"Failed") | F45: =COUNTIF('Grading AI'!$F$12:$F$997,"Pending") | G45: =COUNTIF('Grading AI'!$F$12:$F$997,"N/A") | H45: ='Grading AI'!B4
B46: 36 | C46: =System!B2 | D46: =COUNTIF(System!$F$12:$F$997,"Passed") | E46: =COUNTIF(System!$F$12:$F$997,"Failed") | F46: =COUNTIF(System!$F$12:$F$997,"Pending") | G46: =COUNTIF(System!$F$12:$F$997,"N/A") | H46: =System!B4
B47: 37 | C47: ='Non-functional'!B2 | D47: =COUNTIF('Non-functional'!$F$12:$F$997,"Passed") | E47: =COUNTIF('Non-functional'!$F$12:$F$997,"Failed") | F47: =COUNTIF('Non-functional'!$F$12:$F$997,"Pending") | G47: =COUNTIF('Non-functional'!$F$12:$F$997,"N/A") | H47: ='Non-functional'!B4
C48: Sub total | D48: =SUM(D11:D47) | E48: =SUM(E11:E47) | F48: =SUM(F11:F47) | G48: =SUM(G11:G47) | H48: =SUM(H11:H47)
C50: Test coverage | E50: =(D48+E48)*100/(H48-G48) | F50: %
C51: Test successful coverage | E51: =D48*100/(H48-G48) | F51: %

Sheet Register
A2: Feature | B2: Register
A3: Test requirement | B3: Register learner with email, onboarding data
A4: Number of TCs | B4: =COUNTA(A12:A997)
A5: Testing Round | B5: Passed | C5: Failed | D5: Pending | E5: N/A
A6: Round 1 | B6: =COUNTIF($F$12:$F$997,B$5) | C6: =COUNTIF($F$12:$F$997,C$5) | D6: =COUNTIF($F$12:$F$997,D$5) | E6: =COUNTIF($F$12:$F$997,E$5)
A7: Round 2 | B7: =COUNTIF($I$12:$I$997,B$5) | C7: =COUNTIF($I$12:$I$997,C$5) | D7: =COUNTIF($I$12:$I$997,D$5) | E7: =COUNTIF($I$12:$I$997,E$5)
A8: Round 3 | B8: =COUNTIF($L$12:$L$997,B$5) | C8: =COUNTIF($L$12:$L$997,C$5) | D8: =COUNTIF($L$12:$L$997,D$5) | E8: =COUNTIF($L$12:$L$997,E$5)
A10: Test Case ID | B10: Test Case Description | C10: Test Case Procedure | D10: Expected Results | E10: Pre-conditions | F10: Round 1 | G10: Test date | H10: Tester | I10: Round 2 | J10: Test date | K10: Tester | L10: Round 3 | M10: Test date | N10: Tester | O10: Note
A11: Auth
A12: AUTH-REG-001 | B12: Register learner with valid email, password, onboarding data | C12: Clean test email | D12: POST `auth/register` with valid payload | E12: 201, account + first profile created, tokens returned | F12: Passed | G12: 46127 | H12: Nguyễn Nhật Phát | I12: Passed | J12: 46134 | K12: Nguyễn Trần Tấn Phát | L12: Passed | M12: 46141 | N12: Nguyễn Minh Khôi
A13: AUTH-REG-002 | B13: Register rejects existing email | C13: Email already registered | D13: POST `auth/register` with duplicate email | E13: 422, error message returned | F13: Passed | G13: 46127 | H13: Nguyễn Trần Tấn Phát | I13: Passed | J13: 46134 | K13: Nguyễn Minh Khôi | L13: Passed | M13: 46141 | N13: Hoàng Văn Anh Nghĩa

Sheet Login
A2: Feature | B2: Login
A3: Test requirement | B3: Login with email/password, session, redirect
A4: Number of TCs | B4: =COUNTA(A12:A997)
A5: Testing Round | B5: Passed | C5: Failed | D5: Pending | E5: N/A
A6: Round 1 | B6: =COUNTIF($F$12:$F$997,B$5) | C6: =COUNTIF($F$12:$F$997,C$5) | D6: =COUNTIF($F$12:$F$997,D$5) | E6: =COUNTIF($F$12:$F$997,E$5)
A7: Round 2 | B7: =COUNTIF($I$12:$I$997,B$5) | C7: =COUNTIF($I$12:$I$997,C$5) | D7: =COUNTIF($I$12:$I$997,D$5) | E7: =COUNTIF($I$12:$I$997,E$5)
A8: Round 3 | B8: =COUNTIF($L$12:$L$997,B$5) | C8: =COUNTIF($L$12:$L$997,C$5) | D8: =COUNTIF($L$12:$L$997,D$5) | E8: =COUNTIF($L$12:$L$997,E$5)
A10: Test Case ID | B10: Test Case Description | C10: Test Case Procedure | D10: Expected Results | E10: Pre-conditions | F10: Round 1 | G10: Test date | H10: Tester | I10: Round 2 | J10: Test date | K10: Tester | L10: Round 3 | M10: Test date | N10: Tester | O10: Note
A11: Auth
A12: AUTH-LOGIN-001 | B12: Login learner with correct credentials | C12: Learner account exists | D12: POST `auth/login` with valid email/password | E12: 200, access_token, refresh_token, user, profile returned | F12: Passed | G12: 46127 | H12: Nguyễn Trần Tấn Phát | I12: Passed | J12: 46134 | K12: Nguyễn Minh Khôi | L12: Passed | M12: 46141 | N12: Hoàng Văn Anh Nghĩa
A13: AUTH-LOGIN-002 | B13: Login returns null profile for admin | C13: Admin account exists | D13: POST `auth/login` with admin credentials | E13: 200, profile field is null | F13: Passed | G13: 46127 | H13: Nguyễn Minh Khôi | I13: Passed | J13: 46134 | K13: Hoàng Văn Anh Nghĩa | L13: Passed | M13: 46141 | N13: Nguyễn Nhật Phát
A14: AUTH-LOGIN-003 | B14: Login rejects wrong password | C14: Learner account exists | D14: POST `auth/login` with wrong password | E14: 422, invalid credentials error | F14: Passed | G14: 46127 | H14: Hoàng Văn Anh Nghĩa | I14: Passed | J14: 46134 | K14: Nguyễn Nhật Phát | L14: Passed | M14: 46141 | N14: Nguyễn Trần Tấn Phát
A15: AUTH-LOGIN-005 | B15: Login frontend overlay opens via search param | C15: Frontend app running | D15: Navigate to `/?auth=login` | E15: Landing overlay shows login form | F15: Passed | G15: 46127 | H15: Nguyễn Nhật Phát | I15: Passed | J15: 46134 | K15: Nguyễn Trần Tấn Phát | L15: Passed | M15: 46141 | N15: Nguyễn Minh Khôi
A16: AUTH-LOGIN-006 | B16: Login frontend redirects to dashboard after success | C16: Valid learner in login form | D16: Submit login | E16: Redirect to `/dashboard` | F16: Passed | G16: 46127 | H16: Nguyễn Trần Tấn Phát | I16: Passed | J16: 46134 | K16: Nguyễn Minh Khôi | L16: Passed | M16: 46141 | N16: Hoàng Văn Anh Nghĩa
A17: AUTH-LOGIN-008 | B17: Login frontend rejects non-learner role | C17: Admin account | D17: Submit admin login on learner frontend | E17: Tokens cleared, `roleRejected` set, user stays unauthenticated | F17: Passed | G17: 46127 | H17: Nguyễn Minh Khôi | I17: Passed | J17: 46134 | K17: Hoàng Văn Anh Nghĩa | L17: Passed | M17: 46141 | N17: Nguyễn Nhật Phát

Sheet Google Auth
A2: Feature | B2: Google Login
A3: Test requirement | B3: Google Sign-In integration
A4: Number of TCs | B4: =COUNTA(A12:A997)
A5: Testing Round | B5: Passed | C5: Failed | D5: Pending | E5: N/A
A6: Round 1 | B6: =COUNTIF($F$12:$F$997,B$5) | C6: =COUNTIF($F$12:$F$997,C$5) | D6: =COUNTIF($F$12:$F$997,D$5) | E6: =COUNTIF($F$12:$F$997,E$5)
A7: Round 2 | B7: =COUNTIF($I$12:$I$997,B$5) | C7: =COUNTIF($I$12:$I$997,C$5) | D7: =COUNTIF($I$12:$I$997,D$5) | E7: =COUNTIF($I$12:$I$997,E$5)
A8: Round 3 | B8: =COUNTIF($L$12:$L$997,B$5) | C8: =COUNTIF($L$12:$L$997,C$5) | D8: =COUNTIF($L$12:$L$997,D$5) | E8: =COUNTIF($L$12:$L$997,E$5)
A10: Test Case ID | B10: Test Case Description | C10: Test Case Procedure | D10: Expected Results | E10: Pre-conditions | F10: Round 1 | G10: Test date | H10: Tester | I10: Round 2 | J10: Test date | K10: Tester | L10: Round 3 | M10: Test date | N10: Tester | O10: Note
A11: Auth
A12: AUTH-GOOGLE-001 | B12: Google login for existing learner with profile | C12: Google ID token valid, learner exists with profile | D12: POST `auth/google` with valid token | E12: 200, tokens + user + profile returned | F12: Passed | G12: 46127 | H12: Nguyễn Minh Khôi | I12: Passed | J12: 46134 | K12: Hoàng Văn Anh Nghĩa | L12: Passed | M12: 46141 | N12: Nguyễn Nhật Phát
A13: AUTH-GOOGLE-003 | B13: Google login conflict account exists with different method | C13: Email already registered via password | D13: POST `auth/google` | E13: 409, conflict error | F13: Passed | G13: 46127 | H13: Hoàng Văn Anh Nghĩa | I13: Passed | J13: 46134 | K13: Nguyễn Nhật Phát | L13: Passed | M13: 46141 | N13: Nguyễn Trần Tấn Phát

Sheet Session
A2: Feature | B2: Session & Refresh
A3: Test requirement | B3: Token refresh, logout, lifecycle
A4: Number of TCs | B4: =COUNTA(A12:A997)
A5: Testing Round | B5: Passed | C5: Failed | D5: Pending | E5: N/A
A6: Round 1 | B6: =COUNTIF($F$12:$F$997,B$5) | C6: =COUNTIF($F$12:$F$997,C$5) | D6: =COUNTIF($F$12:$F$997,D$5) | E6: =COUNTIF($F$12:$F$997,E$5)
A7: Round 2 | B7: =COUNTIF($I$12:$I$997,B$5) | C7: =COUNTIF($I$12:$I$997,C$5) | D7: =COUNTIF($I$12:$I$997,D$5) | E7: =COUNTIF($I$12:$I$997,E$5)
A8: Round 3 | B8: =COUNTIF($L$12:$L$997,B$5) | C8: =COUNTIF($L$12:$L$997,C$5) | D8: =COUNTIF($L$12:$L$997,D$5) | E8: =COUNTIF($L$12:$L$997,E$5)
A10: Test Case ID | B10: Test Case Description | C10: Test Case Procedure | D10: Expected Results | E10: Pre-conditions | F10: Round 1 | G10: Test date | H10: Tester | I10: Round 2 | J10: Test date | K10: Tester | L10: Round 3 | M10: Test date | N10: Tester | O10: Note
A11: Auth
A12: AUTH-SESS-001 | B12: Refresh token returns new access token | C12: Valid refresh token | D12: POST `auth/refresh` | E12: 200, new access_token + refresh_token | F12: Passed | G12: 46127 | H12: Hoàng Văn Anh Nghĩa | I12: Passed | J12: 46134 | K12: Nguyễn Nhật Phát | L12: Passed | M12: 46141 | N12: Nguyễn Trần Tấn Phát
A13: AUTH-SESS-002 | B13: Expired/invalid refresh token clears session | C13: Invalid refresh token | D13: POST `auth/refresh` | E13: 422, frontend clears tokens and shows expiration toast | F13: Passed | G13: 46127 | H13: Nguyễn Nhật Phát | I13: Passed | J13: 46134 | K13: Nguyễn Trần Tấn Phát | L13: Passed | M13: 46141 | N13: Nguyễn Minh Khôi
A14: AUTH-SESS-003 | B14: Logout invalidates tokens | C14: Authenticated user | D14: POST `auth/logout` | E14: 204 or 200, tokens no longer accepted | F14: Passed | G14: 46127 | H14: Nguyễn Trần Tấn Phát | I14: Passed | J14: 46134 | K14: Nguyễn Minh Khôi | L14: Passed | M14: 46141 | N14: Hoàng Văn Anh Nghĩa
A15: AUTH-SESS-004 | B15: Protected API rejects missing token | C15: No token | D15: GET `wallet/balance` | E15: 401 | F15: Passed | G15: 46127 | H15: Nguyễn Minh Khôi | I15: Passed | J15: 46134 | K15: Hoàng Văn Anh Nghĩa | L15: Passed | M15: 46141 | N15: Nguyễn Nhật Phát
A16: AUTH-SESS-007 | B16: Frontend redirects unauthenticated user to login | C16: No tokens | D16: Navigate to `/dashboard` | E16: Redirect to `/?auth=login&redirect=/dashboard` | F16: Passed | G16: 46127 | H16: Hoàng Văn Anh Nghĩa | I16: Passed | J16: 46134 | K16: Nguyễn Nhật Phát | L16: Passed | M16: 46141 | N16: Nguyễn Trần Tấn Phát

Sheet Profile
A2: Feature | B2: Profile CRUD
A3: Test requirement | B3: List, create, switch, update, onboarding
A4: Number of TCs | B4: =COUNTA(A12:A997)
A5: Testing Round | B5: Passed | C5: Failed | D5: Pending | E5: N/A
A6: Round 1 | B6: =COUNTIF($F$12:$F$997,B$5) | C6: =COUNTIF($F$12:$F$997,C$5) | D6: =COUNTIF($F$12:$F$997,D$5) | E6: =COUNTIF($F$12:$F$997,E$5)
A7: Round 2 | B7: =COUNTIF($I$12:$I$997,B$5) | C7: =COUNTIF($I$12:$I$997,C$5) | D7: =COUNTIF($I$12:$I$997,D$5) | E7: =COUNTIF($I$12:$I$997,E$5)
A8: Round 3 | B8: =COUNTIF($L$12:$L$997,B$5) | C8: =COUNTIF($L$12:$L$997,C$5) | D8: =COUNTIF($L$12:$L$997,D$5) | E8: =COUNTIF($L$12:$L$997,E$5)
A10: Test Case ID | B10: Test Case Description | C10: Test Case Procedure | D10: Expected Results | E10: Pre-conditions | F10: Round 1 | G10: Test date | H10: Tester | I10: Round 2 | J10: Test date | K10: Tester | L10: Round 3 | M10: Test date | N10: Tester | O10: Note
A11: Profile
A12: PROF-001 | B12: List profiles for authenticated account | C12: Account with multiple profiles | D12: GET `profiles` | E12: 200, list of owned profiles | F12: Passed | G12: 46127 | H12: Nguyễn Nhật Phát | I12: Passed | J12: 46134 | K12: Nguyễn Trần Tấn Phát | L12: Passed | M12: 46141 | N12: Nguyễn Minh Khôi
A13: PROF-002 | B13: Create new learning profile | C13: Authenticated account | D13: POST `profiles` with target/level/deadline | E13: 201, new profile created | F13: Passed | G13: 46127 | H13: Nguyễn Trần Tấn Phát | I13: Passed | J13: 46134 | K13: Nguyễn Minh Khôi | L13: Passed | M13: 46141 | N13: Hoàng Văn Anh Nghĩa
A14: PROF-003 | B14: Switch active profile | C14: Multiple profiles exist | D14: POST `auth/switch-profile` | E14: 200, active profile changes, subsequent API calls use new profile context | F14: Passed | G14: 46127 | H14: Nguyễn Minh Khôi | I14: Passed | J14: 46134 | K14: Hoàng Văn Anh Nghĩa | L14: Passed | M14: 46141 | N14: Nguyễn Nhật Phát
A15: PROF-004 | B15: Update profile info via frontend | C15: Profile exists | D15: Open ho-so, edit profile, save | E15: Profile updated, data persisted | F15: Passed | G15: 46127 | H15: Hoàng Văn Anh Nghĩa | I15: Passed | J15: 46134 | K15: Nguyễn Nhật Phát | L15: Passed | M15: 46141 | N15: Nguyễn Trần Tấn Phát
A16: PROF-006 | B16: Cannot access another account's profile | C16: Account A has profile | D16: Account B tries to update account A's profile | E16: 403 or 404 | F16: Passed | G16: 46127 | H16: Nguyễn Nhật Phát | I16: Passed | J16: 46134 | K16: Nguyễn Trần Tấn Phát | L16: Passed | M16: 46141 | N16: Nguyễn Minh Khôi
A17: PROF-008 | B17: Complete onboarding via API | C17: Authenticated without active profile | D17: POST `profiles/{id}/onboarding` with nickname/level/deadline | E17: 200, onboarding bonus granted if applicable (100 coins) | F17: Passed | G17: 46127 | H17: Nguyễn Trần Tấn Phát | I17: Passed | J17: 46134 | K17: Nguyễn Minh Khôi | L17: Passed | M17: 46141 | N17: Hoàng Văn Anh Nghĩa
A18: PROF-009 | B18: Change password | C18: Authenticated | D18: POST `me/change-password` with old + new password | E18: 200, password updated, re-login required | F18: Passed | G18: 46127 | H18: Nguyễn Minh Khôi | I18: Passed | J18: 46134 | K18: Hoàng Văn Anh Nghĩa | L18: Passed | M18: 46141 | N18: Nguyễn Nhật Phát
A19: PROF-010 | B19: Avatar upload | C19: Authenticated with active profile | D19: POST `me/avatar` with valid image | E19: 200, avatar URL updated | F19: Passed | G19: 46127 | H19: Hoàng Văn Anh Nghĩa | I19: Passed | J19: 46134 | K19: Nguyễn Nhật Phát | L19: Passed | M19: 46141 | N19: Nguyễn Trần Tấn Phát

Sheet Vocabulary
A2: Feature | B2: Vocabulary & SRS
A3: Test requirement | B3: Topic list, detail, exercises, SRS review
A4: Number of TCs | B4: =COUNTA(A12:A997)
A5: Testing Round | B5: Passed | C5: Failed | D5: Pending | E5: N/A
A6: Round 1 | B6: =COUNTIF($F$12:$F$997,B$5) | C6: =COUNTIF($F$12:$F$997,C$5) | D6: =COUNTIF($F$12:$F$997,D$5) | E6: =COUNTIF($F$12:$F$997,E$5)
A7: Round 2 | B7: =COUNTIF($I$12:$I$997,B$5) | C7: =COUNTIF($I$12:$I$997,C$5) | D7: =COUNTIF($I$12:$I$997,D$5) | E7: =COUNTIF($I$12:$I$997,E$5)
A8: Round 3 | B8: =COUNTIF($L$12:$L$997,B$5) | C8: =COUNTIF($L$12:$L$997,C$5) | D8: =COUNTIF($L$12:$L$997,D$5) | E8: =COUNTIF($L$12:$L$997,E$5)
A10: Test Case ID | B10: Test Case Description | C10: Test Case Procedure | D10: Expected Results | E10: Pre-conditions | F10: Round 1 | G10: Test date | H10: Tester | I10: Round 2 | J10: Test date | K10: Tester | L10: Round 3 | M10: Test date | N10: Tester | O10: Note
A11: Vocab
A12: VOC-001 | B12: List vocabulary topics | C12: Topics seeded in DB | D12: GET `vocab/topics` | E12: 200, topics list with publish status, word count | F12: Passed | G12: 46127 | H12: Nguyễn Trần Tấn Phát | I12: Passed | J12: 46134 | K12: Nguyễn Minh Khôi | L12: Passed | M12: 46141 | N12: Hoàng Văn Anh Nghĩa
A13: VOC-002 | B13: Show vocabulary topic detail | C13: Published topic exists | D13: GET `vocab/topics/{id}` | E13: 200, topic with words list, progress info | F13: Passed | G13: 46127 | H13: Nguyễn Minh Khôi | I13: Passed | J13: 46134 | K13: Hoàng Văn Anh Nghĩa | L13: Passed | M13: 46141 | N13: Nguyễn Nhật Phát
A14: VOC-EX-004 | B14: Frontend exercise flow (MCQ + fill-blank) | C14: Topic has exercises | D14: Open exercise, answer, submit | E14: Result displayed, progress updated | F14: Passed | G14: 46127 | H14: Hoàng Văn Anh Nghĩa | I14: Passed | J14: 46134 | K14: Nguyễn Nhật Phát | L14: Passed | M14: 46141 | N14: Nguyễn Trần Tấn Phát
A15: VOC-SRS-001 | B15: SRS queue returns due cards | C15: Words previously learned, due for review | D15: GET `vocab/srs/queue` | E15: 200, list of due review items | F15: Passed | G15: 46127 | H15: Nguyễn Nhật Phát | I15: Passed | J15: 46134 | K15: Nguyễn Trần Tấn Phát | L15: Passed | M15: 46141 | N15: Nguyễn Minh Khôi
A16: VOC-SRS-002 | B16: SRS review updates scheduling | C16: Due word in queue | D16: POST `vocab/srs/review` with word_id and rating (good/again) | E16: 200, due date updated via FSRS algorithm | F16: Passed | G16: 46127 | H16: Nguyễn Trần Tấn Phát | I16: Passed | J16: 46134 | K16: Nguyễn Minh Khôi | L16: Passed | M16: 46141 | N16: Hoàng Văn Anh Nghĩa
A17: VOC-SRS-004 | B17: Frontend SRS review flow | C17: Due cards exist | D17: Open focused SRS review, rate cards | E17: Cards rated, queue updated, progress saved | F17: Passed | G17: 46127 | H17: Nguyễn Minh Khôi | I17: Passed | J17: 46134 | K17: Hoàng Văn Anh Nghĩa | L17: Passed | M17: 46141 | N17: Nguyễn Nhật Phát
A18: VOC-SRS-006 | B18: FSRS scheduler computes correct intervals | C18: Unit test | D18: Call scheduler with new/learning/review states | E18: Intervals match FSRS formula, state transitions correct | F18: Passed | G18: 46127 | H18: Hoàng Văn Anh Nghĩa | I18: Passed | J18: 46134 | K18: Nguyễn Nhật Phát | L18: Passed | M18: 46141 | N18: Nguyễn Trần Tấn Phát

Sheet Grammar
A2: Feature | B2: Grammar Points
A3: Test requirement | B3: Point list, detail, exercise flow
A4: Number of TCs | B4: =COUNTA(A12:A997)
A5: Testing Round | B5: Passed | C5: Failed | D5: Pending | E5: N/A
A6: Round 1 | B6: =COUNTIF($F$12:$F$997,B$5) | C6: =COUNTIF($F$12:$F$997,C$5) | D6: =COUNTIF($F$12:$F$997,D$5) | E6: =COUNTIF($F$12:$F$997,E$5)
A7: Round 2 | B7: =COUNTIF($I$12:$I$997,B$5) | C7: =COUNTIF($I$12:$I$997,C$5) | D7: =COUNTIF($I$12:$I$997,D$5) | E7: =COUNTIF($I$12:$I$997,E$5)
A8: Round 3 | B8: =COUNTIF($L$12:$L$997,B$5) | C8: =COUNTIF($L$12:$L$997,C$5) | D8: =COUNTIF($L$12:$L$997,D$5) | E8: =COUNTIF($L$12:$L$997,E$5)
A10: Test Case ID | B10: Test Case Description | C10: Test Case Procedure | D10: Expected Results | E10: Pre-conditions | F10: Round 1 | G10: Test date | H10: Tester | I10: Round 2 | J10: Test date | K10: Tester | L10: Round 3 | M10: Test date | N10: Tester | O10: Note
A11: Grammar
A12: GRAM-001 | B12: List grammar points | C12: Points seeded in DB | D12: GET `grammar/points` | E12: 200, points list with publish status | F12: Passed | G12: 46127 | H12: Nguyễn Minh Khôi | I12: Passed | J12: 46134 | K12: Hoàng Văn Anh Nghĩa | L12: Passed | M12: 46141 | N12: Nguyễn Nhật Phát
A13: GRAM-002 | B13: Show grammar point detail | C13: Published point exists | D13: GET `grammar/points/{id}` | E13: 200, point with structures/examples/mistakes/tips | F13: Passed | G13: 46127 | H13: Hoàng Văn Anh Nghĩa | I13: Passed | J13: 46134 | K13: Nguyễn Nhật Phát | L13: Passed | M13: 46141 | N13: Nguyễn Trần Tấn Phát
A14: GRAM-EX-002 | B14: Frontend grammar exercise flow | C14: Point with exercise | D14: Open exercise, answer questions, submit | E14: Instant feedback, result summary, retry option | F14: Passed | G14: 46127 | H14: Nguyễn Nhật Phát | I14: Passed | J14: 46134 | K14: Nguyễn Trần Tấn Phát | L14: Passed | M14: 46141 | N14: Nguyễn Minh Khôi
A15: GRAM-EX-004 | B15: Grammar exercise handles retry | C15: Previously completed exercise | D15: Click retry | E15: New session started, fresh answers | F15: Passed | G15: 46127 | H15: Nguyễn Trần Tấn Phát | I15: Passed | J15: 46134 | K15: Nguyễn Minh Khôi | L15: Passed | M15: 46141 | N15: Hoàng Văn Anh Nghĩa

Sheet Listening
A2: Feature | B2: Listening Practice
A3: Test requirement | B3: Exercise list, audio, answer, results
A4: Number of TCs | B4: =COUNTA(A12:A997)
A5: Testing Round | B5: Passed | C5: Failed | D5: Pending | E5: N/A
A6: Round 1 | B6: =COUNTIF($F$12:$F$997,B$5) | C6: =COUNTIF($F$12:$F$997,C$5) | D6: =COUNTIF($F$12:$F$997,D$5) | E6: =COUNTIF($F$12:$F$997,E$5)
A7: Round 2 | B7: =COUNTIF($I$12:$I$997,B$5) | C7: =COUNTIF($I$12:$I$997,C$5) | D7: =COUNTIF($I$12:$I$997,D$5) | E7: =COUNTIF($I$12:$I$997,E$5)
A8: Round 3 | B8: =COUNTIF($L$12:$L$997,B$5) | C8: =COUNTIF($L$12:$L$997,C$5) | D8: =COUNTIF($L$12:$L$997,D$5) | E8: =COUNTIF($L$12:$L$997,E$5)
A10: Test Case ID | B10: Test Case Description | C10: Test Case Procedure | D10: Expected Results | E10: Pre-conditions | F10: Round 1 | G10: Test date | H10: Tester | I10: Round 2 | J10: Test date | K10: Tester | L10: Round 3 | M10: Test date | N10: Tester | O10: Note
A11: Practice
A12: PRAC-LIS-001 | B12: List listening exercises | C12: Listening exercises exist | D12: GET `practice/listening/exercises` | E12: 200, exercise list with level/estimated minutes | F12: Passed | G12: 46127 | H12: Hoàng Văn Anh Nghĩa | I12: Passed | J12: 46134 | K12: Nguyễn Nhật Phát | L12: Passed | M12: 46141 | N12: Nguyễn Trần Tấn Phát
A13: PRAC-LIS-002 | B13: Show listening exercise detail | C13: Exercise exists with audio | D13: GET `practice/listening/exercises/{id}` | E13: 200, exercise with audio_url, transcript, questions | F13: Passed | G13: 46127 | H13: Nguyễn Nhật Phát | I13: Passed | J13: 46134 | K13: Nguyễn Trần Tấn Phát | L13: Passed | M13: 46141 | N13: Nguyễn Minh Khôi
A14: PRAC-LIS-004 | B14: Answer listening MCQ questions | C14: Active session | D14: POST `practice/listening/sessions/{id}/submit` with answers | E14: 200, score calculated, correct/incorrect per question | F14: Passed | G14: 46127 | H14: Nguyễn Trần Tấn Phát | I14: Passed | J14: 46134 | K14: Nguyễn Minh Khôi | L14: Passed | M14: 46141 | N14: Hoàng Văn Anh Nghĩa
A15: PRAC-LIS-006 | B15: Frontend listening exercise list with filters | C15: Exercises with different levels | D15: Open listening page, apply level filter | E15: Filtered list, exercise cards with progress | F15: Passed | G15: 46127 | H15: Nguyễn Minh Khôi | I15: Passed | J15: 46134 | K15: Hoàng Văn Anh Nghĩa | L15: Passed | M15: 46141 | N15: Nguyễn Nhật Phát
A16: PRAC-LIS-007 | B16: Frontend listening answers show results | C16: Active session | D16: Answer questions in focused screen | E16: Correct/wrong feedback, score, transcript shown | F16: Passed | G16: 46127 | H16: Hoàng Văn Anh Nghĩa | I16: Passed | J16: 46134 | K16: Nguyễn Nhật Phát | L16: Passed | M16: 46141 | N16: Nguyễn Trần Tấn Phát
A17: PRAC-SKILLS-001 | B17: Practice skills page renders all skills | C17: Authenticated learner | D17: Open `/luyen-tap` | E17: Listening, Reading, Writing, Speaking, Vocab, Grammar sections visible | F17: Passed | G17: 46127 | H17: Nguyễn Nhật Phát | I17: Passed | J17: 46134 | K17: Nguyễn Trần Tấn Phát | L17: Passed | M17: 46141 | N17: Nguyễn Minh Khôi

Sheet Reading
A2: Feature | B2: Reading Practice
A3: Test requirement | B3: Exercise list, passage, questions, results
A4: Number of TCs | B4: =COUNTA(A12:A997)
A5: Testing Round | B5: Passed | C5: Failed | D5: Pending | E5: N/A
A6: Round 1 | B6: =COUNTIF($F$12:$F$997,B$5) | C6: =COUNTIF($F$12:$F$997,C$5) | D6: =COUNTIF($F$12:$F$997,D$5) | E6: =COUNTIF($F$12:$F$997,E$5)
A7: Round 2 | B7: =COUNTIF($I$12:$I$997,B$5) | C7: =COUNTIF($I$12:$I$997,C$5) | D7: =COUNTIF($I$12:$I$997,D$5) | E7: =COUNTIF($I$12:$I$997,E$5)
A8: Round 3 | B8: =COUNTIF($L$12:$L$997,B$5) | C8: =COUNTIF($L$12:$L$997,C$5) | D8: =COUNTIF($L$12:$L$997,D$5) | E8: =COUNTIF($L$12:$L$997,E$5)
A10: Test Case ID | B10: Test Case Description | C10: Test Case Procedure | D10: Expected Results | E10: Pre-conditions | F10: Round 1 | G10: Test date | H10: Tester | I10: Round 2 | J10: Test date | K10: Tester | L10: Round 3 | M10: Test date | N10: Tester | O10: Note
A11: Practice
A12: PRAC-REA-001 | B12: List reading exercises | C12: Reading exercises exist | D12: GET `practice/reading/exercises` | E12: 200, exercise list with metadata | F12: Passed | G12: 46127 | H12: Nguyễn Nhật Phát | I12: Passed | J12: 46134 | K12: Nguyễn Trần Tấn Phát | L12: Passed | M12: 46141 | N12: Nguyễn Minh Khôi
A13: PRAC-REA-002 | B13: Show reading exercise detail | C13: Exercise exists with passage + questions | D13: GET `practice/reading/exercises/{id}` | E13: 200, passage, questions, options | F13: Passed | G13: 46127 | H13: Nguyễn Trần Tấn Phát | I13: Passed | J13: 46134 | K13: Nguyễn Minh Khôi | L13: Passed | M13: 46141 | N13: Hoàng Văn Anh Nghĩa
A14: PRAC-REA-004 | B14: Answer reading MCQ questions | C14: Active session | D14: POST `practice/reading/sessions/{id}/submit` | E14: 200, score + correct/incorrect per question | F14: Passed | G14: 46127 | H14: Nguyễn Minh Khôi | I14: Passed | J14: 46134 | K14: Hoàng Văn Anh Nghĩa | L14: Passed | M14: 46141 | N14: Nguyễn Nhật Phát
A15: PRAC-REA-005 | B15: Frontend reading exercise with passage | C15: Exercise has passage | D15: Open reading exercise | E15: Passage displayed, questions alongside, answer selection | F15: Passed | G15: 46127 | H15: Hoàng Văn Anh Nghĩa | I15: Passed | J15: 46134 | K15: Nguyễn Nhật Phát | L15: Passed | M15: 46141 | N15: Nguyễn Trần Tấn Phát
A16: PRAC-REA-007 | B16: Frontend reading answers show results | C16: Active session, all questions answered | D16: Submit | E16: Score, per-question results, passage with highlights | F16: Passed | G16: 46127 | H16: Nguyễn Nhật Phát | I16: Passed | J16: 46134 | K16: Nguyễn Trần Tấn Phát | L16: Passed | M16: 46141 | N16: Nguyễn Minh Khôi

Sheet Writing
A2: Feature | B2: Writing Practice
A3: Test requirement | B3: Prompt, editor, submit, AI feedback, SSE
A4: Number of TCs | B4: =COUNTA(A12:A997)
A5: Testing Round | B5: Passed | C5: Failed | D5: Pending | E5: N/A
A6: Round 1 | B6: =COUNTIF($F$12:$F$997,B$5) | C6: =COUNTIF($F$12:$F$997,C$5) | D6: =COUNTIF($F$12:$F$997,D$5) | E6: =COUNTIF($F$12:$F$997,E$5)
A7: Round 2 | B7: =COUNTIF($I$12:$I$997,B$5) | C7: =COUNTIF($I$12:$I$997,C$5) | D7: =COUNTIF($I$12:$I$997,D$5) | E7: =COUNTIF($I$12:$I$997,E$5)
A8: Round 3 | B8: =COUNTIF($L$12:$L$997,B$5) | C8: =COUNTIF($L$12:$L$997,C$5) | D8: =COUNTIF($L$12:$L$997,D$5) | E8: =COUNTIF($L$12:$L$997,E$5)
A10: Test Case ID | B10: Test Case Description | C10: Test Case Procedure | D10: Expected Results | E10: Pre-conditions | F10: Round 1 | G10: Test date | H10: Tester | I10: Round 2 | J10: Test date | K10: Tester | L10: Round 3 | M10: Test date | N10: Tester | O10: Note
A11: Practice
A12: WRI-001 | B12: List writing prompts | C12: Prompts exist | D12: GET `practice/writing/prompts` | E12: 200, list with title, level, task type, estimated minutes | F12: Passed | G12: 46127 | H12: Nguyễn Trần Tấn Phát | I12: Passed | J12: 46134 | K12: Nguyễn Minh Khôi | L12: Passed | M12: 46141 | N12: Hoàng Văn Anh Nghĩa
A13: WRI-004 | B13: Submit writing answer | C13: Active session | D13: POST `practice/writing/sessions/{id}/submit` with text | E13: 200, submission accepted, feedback job triggered | F13: Passed | G13: 46127 | H13: Nguyễn Minh Khôi | I13: Passed | J13: 46134 | K13: Hoàng Văn Anh Nghĩa | L13: Passed | M13: 46141 | N13: Nguyễn Nhật Phát
A14: WRI-005 | B14: Submit writing answer below min_words | C14: Active session, min_words config exists | D14: Submit text shorter than min_words | E14: 422, validation error for word count | F14: Passed | G14: 46127 | H14: Hoàng Văn Anh Nghĩa | I14: Passed | J14: 46134 | K14: Nguyễn Nhật Phát | L14: Passed | M14: 46141 | N14: Nguyễn Trần Tấn Phát
A15: WRI-007 | B15: Generate AI feedback for writing submission | C15: Submitted writing, AI service available | D15: POST `practice/writing/submissions/{id}/feedback` | E15: 201 or 200, grading job created, SSE stream available | F15: Passed | G15: 46127 | H15: Nguyễn Nhật Phát | I15: Passed | J15: 46134 | K15: Nguyễn Trần Tấn Phát | L15: Passed | M15: 46141 | N15: Nguyễn Minh Khôi
A16: WRI-008 | B16: Writing feedback SSE receives completion | C16: Grading job active | D16: Connect to grading job stream | E16: Progress events, scores event, feedback event, done event | F16: Passed | G16: 46127 | H16: Nguyễn Trần Tấn Phát | I16: Passed | J16: 46134 | K16: Nguyễn Minh Khôi | L16: Passed | M16: 46141 | N16: Hoàng Văn Anh Nghĩa
A17: WRI-010 | B17: Frontend writing editor with word count | C17: Prompt detail page | D17: Type text | E17: Word count updates, min_word progress bar, validation messages | F17: Passed | G17: 46127 | H17: Nguyễn Minh Khôi | I17: Passed | J17: 46134 | K17: Hoàng Văn Anh Nghĩa | L17: Passed | M17: 46141 | N17: Nguyễn Nhật Phát
A18: WRI-011 | B18: Frontend writing grading screen | C18: Submitted writing, grading in progress | D18: Wait for feedback | E18: Pending → scoring → feedback phases, overall band, rubric dimensions | F18: Passed | G18: 46127 | H18: Hoàng Văn Anh Nghĩa | I18: Passed | J18: 46134 | K18: Nguyễn Nhật Phát | L18: Passed | M18: 46141 | N18: Nguyễn Trần Tấn Phát
A19: WRI-012 | B19: Frontend writing result displays sections | C19: Graded writing with feedback | D19: Open writing result | E19: Strengths, Improvements, Rewrites sections displayed | F19: Passed | G19: 46127 | H19: Nguyễn Nhật Phát | I19: Passed | J19: 46134 | K19: Nguyễn Trần Tấn Phát | L19: Passed | M19: 46141 | N19: Nguyễn Minh Khôi

Sheet Speaking Drills
A2: Feature | B2: Speaking Drills
A3: Test requirement | B3: Pronunciation drill, recording, feedback
A4: Number of TCs | B4: =COUNTA(A12:A997)
A5: Testing Round | B5: Passed | C5: Failed | D5: Pending | E5: N/A
A6: Round 1 | B6: =COUNTIF($F$12:$F$997,B$5) | C6: =COUNTIF($F$12:$F$997,C$5) | D6: =COUNTIF($F$12:$F$997,D$5) | E6: =COUNTIF($F$12:$F$997,E$5)
A7: Round 2 | B7: =COUNTIF($I$12:$I$997,B$5) | C7: =COUNTIF($I$12:$I$997,C$5) | D7: =COUNTIF($I$12:$I$997,D$5) | E7: =COUNTIF($I$12:$I$997,E$5)
A8: Round 3 | B8: =COUNTIF($L$12:$L$997,B$5) | C8: =COUNTIF($L$12:$L$997,C$5) | D8: =COUNTIF($L$12:$L$997,D$5) | E8: =COUNTIF($L$12:$L$997,E$5)
A10: Test Case ID | B10: Test Case Description | C10: Test Case Procedure | D10: Expected Results | E10: Pre-conditions | F10: Round 1 | G10: Test date | H10: Tester | I10: Round 2 | J10: Test date | K10: Tester | L10: Round 3 | M10: Test date | N10: Tester | O10: Note
A11: Practice
A12: SPK-DRL-004 | B12: Record drill attempt with audio | C12: Active drill session | D12: POST `practice/speaking/drill-sessions/{id}/attempt` with audio file | E12: 200, attempt recorded, pronunciation/fluency feedback | F12: Passed | G12: 46127 | H12: Nguyễn Minh Khôi | I12: Passed | J12: 46134 | K12: Hoàng Văn Anh Nghĩa | L12: Passed | M12: 46141 | N12: Nguyễn Nhật Phát
A13: SPK-DRL-006 | B13: Frontend speaking drill list with filters | C13: Drills with different levels | D13: Open speaking practice, drills tab | E13: Drills displayed, level filters, practice history link | F13: Passed | G13: 46127 | H13: Hoàng Văn Anh Nghĩa | I13: Passed | J13: 46134 | K13: Nguyễn Nhật Phát | L13: Passed | M13: 46141 | N13: Nguyễn Trần Tấn Phát

Sheet VSTEP Speaking
A2: Feature | B2: VSTEP Speaking
A3: Test requirement | B3: VSTEP session, submit, grading
A4: Number of TCs | B4: =COUNTA(A12:A997)
A5: Testing Round | B5: Passed | C5: Failed | D5: Pending | E5: N/A
A6: Round 1 | B6: =COUNTIF($F$12:$F$997,B$5) | C6: =COUNTIF($F$12:$F$997,C$5) | D6: =COUNTIF($F$12:$F$997,D$5) | E6: =COUNTIF($F$12:$F$997,E$5)
A7: Round 2 | B7: =COUNTIF($I$12:$I$997,B$5) | C7: =COUNTIF($I$12:$I$997,C$5) | D7: =COUNTIF($I$12:$I$997,D$5) | E7: =COUNTIF($I$12:$I$997,E$5)
A8: Round 3 | B8: =COUNTIF($L$12:$L$997,B$5) | C8: =COUNTIF($L$12:$L$997,C$5) | D8: =COUNTIF($L$12:$L$997,D$5) | E8: =COUNTIF($L$12:$L$997,E$5)
A10: Test Case ID | B10: Test Case Description | C10: Test Case Procedure | D10: Expected Results | E10: Pre-conditions | F10: Round 1 | G10: Test date | H10: Tester | I10: Round 2 | J10: Test date | K10: Tester | L10: Round 3 | M10: Test date | N10: Tester | O10: Note
A11: Practice
A12: SPK-VST-004 | B12: Submit VSTEP speaking session | C12: Active session | D12: POST `practice/speaking/vstep-sessions/{id}/submit` with audio answers | E12: 200, submission accepted, grading job triggered | F12: Passed | G12: 46127 | H12: Hoàng Văn Anh Nghĩa | I12: Passed | J12: 46134 | K12: Nguyễn Nhật Phát | L12: Passed | M12: 46141 | N12: Nguyễn Trần Tấn Phát
A13: SPK-VST-006 | B13: Frontend VSTEP speaking task practice | C13: Task exists in web app | D13: Select task, record per part, submit | E13: Submit confirmation, waiting for grading | F13: Passed | G13: 46127 | H13: Nguyễn Nhật Phát | I13: Passed | J13: 46134 | K13: Nguyễn Trần Tấn Phát | L13: Passed | M13: 46141 | N13: Nguyễn Minh Khôi

Sheet Conversation AI
A2: Feature | B2: Conversation
A3: Test requirement | B3: Scenario start, turns, review, feedback
A4: Number of TCs | B4: =COUNTA(A12:A997)
A5: Testing Round | B5: Passed | C5: Failed | D5: Pending | E5: N/A
A6: Round 1 | B6: =COUNTIF($F$12:$F$997,B$5) | C6: =COUNTIF($F$12:$F$997,C$5) | D6: =COUNTIF($F$12:$F$997,D$5) | E6: =COUNTIF($F$12:$F$997,E$5)
A7: Round 2 | B7: =COUNTIF($I$12:$I$997,B$5) | C7: =COUNTIF($I$12:$I$997,C$5) | D7: =COUNTIF($I$12:$I$997,D$5) | E7: =COUNTIF($I$12:$I$997,E$5)
A8: Round 3 | B8: =COUNTIF($L$12:$L$997,B$5) | C8: =COUNTIF($L$12:$L$997,C$5) | D8: =COUNTIF($L$12:$L$997,D$5) | E8: =COUNTIF($L$12:$L$997,E$5)
A10: Test Case ID | B10: Test Case Description | C10: Test Case Procedure | D10: Expected Results | E10: Pre-conditions | F10: Round 1 | G10: Test date | H10: Tester | I10: Round 2 | J10: Test date | K10: Tester | L10: Round 3 | M10: Test date | N10: Tester | O10: Note
A11: Practice
A12: SPK-CONV-003 | B12: Start conversation session | C12: Scenario exists, authenticated | D12: POST `practice/speaking/conversations` | E12: 201, conversation session with first AI turn | F12: Passed | G12: 46127 | H12: Nguyễn Nhật Phát | I12: Passed | J12: 46134 | K12: Nguyễn Trần Tấn Phát | L12: Passed | M12: 46141 | N12: Nguyễn Minh Khôi
A13: SPK-CONV-004 | B13: Send conversation turn | C13: Active conversation | D13: POST `practice/speaking/conversations/{id}/turn` with audio + text | E13: 200, AI responds with next turn | F13: Passed | G13: 46127 | H13: Nguyễn Trần Tấn Phát | I13: Passed | J13: 46134 | K13: Nguyễn Minh Khôi | L13: Passed | M13: 46141 | N13: Hoàng Văn Anh Nghĩa
A14: SPK-CONV-006 | B14: Conversation review with feedback | C14: Ended conversation | D14: GET `practice/speaking/conversations/{id}/review` | E14: 200, review with content relevance, task fulfillment, pronunciation, feedback per turn | F14: Passed | G14: 46127 | H14: Nguyễn Minh Khôi | I14: Passed | J14: 46134 | K14: Hoàng Văn Anh Nghĩa | L14: Passed | M14: 46141 | N14: Nguyễn Nhật Phát
A15: SPK-CONV-008 | B15: Frontend conversation flow | C15: Scenario selected | D15: Start scenario, speak/respond, end conversation | E15: Turn-by-turn UI, review popup with feedback | F15: Passed | G15: 46127 | H15: Hoàng Văn Anh Nghĩa | I15: Passed | J15: 46134 | K15: Nguyễn Nhật Phát | L15: Passed | M15: 46141 | N15: Nguyễn Trần Tấn Phát

Sheet Shadowing
A2: Feature | B2: Shadowing
A3: Test requirement | B3: Shadowing session, playback, recording
A4: Number of TCs | B4: =COUNTA(A12:A997)
A5: Testing Round | B5: Passed | C5: Failed | D5: Pending | E5: N/A
A6: Round 1 | B6: =COUNTIF($F$12:$F$997,B$5) | C6: =COUNTIF($F$12:$F$997,C$5) | D6: =COUNTIF($F$12:$F$997,D$5) | E6: =COUNTIF($F$12:$F$997,E$5)
A7: Round 2 | B7: =COUNTIF($I$12:$I$997,B$5) | C7: =COUNTIF($I$12:$I$997,C$5) | D7: =COUNTIF($I$12:$I$997,D$5) | E7: =COUNTIF($I$12:$I$997,E$5)
A8: Round 3 | B8: =COUNTIF($L$12:$L$997,B$5) | C8: =COUNTIF($L$12:$L$997,C$5) | D8: =COUNTIF($L$12:$L$997,D$5) | E8: =COUNTIF($L$12:$L$997,E$5)
A10: Test Case ID | B10: Test Case Description | C10: Test Case Procedure | D10: Expected Results | E10: Pre-conditions | F10: Round 1 | G10: Test date | H10: Tester | I10: Round 2 | J10: Test date | K10: Tester | L10: Round 3 | M10: Test date | N10: Tester | O10: Note
A11: Practice
A12: SPK-SHA-003 | B12: Frontend shadowing session | C12: Lesson exists | D12: Open shadowing lesson, play audio, record, compare | E12: Segment-by-segment flow, pronunciation feedback | F12: Passed | G12: 46127 | H12: Nguyễn Trần Tấn Phát | I12: Passed | J12: 46134 | K12: Nguyễn Minh Khôi | L12: Passed | M12: 46141 | N12: Hoàng Văn Anh Nghĩa

Sheet Exam Library
A2: Feature | B2: Exam Library & Detail
A3: Test requirement | B3: List, status cards, detail, skill selector
A4: Number of TCs | B4: =COUNTA(A12:A997)
A5: Testing Round | B5: Passed | C5: Failed | D5: Pending | E5: N/A
A6: Round 1 | B6: =COUNTIF($F$12:$F$997,B$5) | C6: =COUNTIF($F$12:$F$997,C$5) | D6: =COUNTIF($F$12:$F$997,D$5) | E6: =COUNTIF($F$12:$F$997,E$5)
A7: Round 2 | B7: =COUNTIF($I$12:$I$997,B$5) | C7: =COUNTIF($I$12:$I$997,C$5) | D7: =COUNTIF($I$12:$I$997,D$5) | E7: =COUNTIF($I$12:$I$997,E$5)
A8: Round 3 | B8: =COUNTIF($L$12:$L$997,B$5) | C8: =COUNTIF($L$12:$L$997,C$5) | D8: =COUNTIF($L$12:$L$997,D$5) | E8: =COUNTIF($L$12:$L$997,E$5)
A10: Test Case ID | B10: Test Case Description | C10: Test Case Procedure | D10: Expected Results | E10: Pre-conditions | F10: Round 1 | G10: Test date | H10: Tester | I10: Round 2 | J10: Test date | K10: Tester | L10: Round 3 | M10: Test date | N10: Tester | O10: Note
A11: Exam
A12: EXAM-LIB-001 | B12: List published exams with config and sessions | C12: Published exams exist, authenticated learner | D12: GET `exams`, GET `config`, GET `exam-sessions` | E12: Exam cards show with status: not-started/in-progress/submitted | F12: Passed | G12: 46127 | H12: Nguyễn Minh Khôi | I12: Passed | J12: 46134 | K12: Hoàng Văn Anh Nghĩa | L12: Passed | M12: 46141 | N12: Nguyễn Nhật Phát
A13: EXAM-LIB-003 | B13: Filter exam by status all/not-started/in-progress/submitted | C13: Mixed status exams | D13: Switch filter tab, URL search param `status` updates | E13: Correct cards displayed, tab counts update | F13: Passed | G13: 46127 | H13: Hoàng Văn Anh Nghĩa | I13: Passed | J13: 46134 | K13: Nguyễn Nhật Phát | L13: Passed | M13: 46141 | N13: Nguyễn Trần Tấn Phát
A14: EXAM-DET-001 | B14: Show exam detail with sections | C14: Published exam with version | D14: GET `exams/{id}` | E14: 200, exam detail with version, listening/reading/writing/speaking sections, session history | F14: Passed | G14: 46127 | H14: Nguyễn Nhật Phát | I14: Passed | J14: 46134 | K14: Nguyễn Trần Tấn Phát | L14: Passed | M14: 46141 | N14: Nguyễn Minh Khôi
A15: EXAM-DET-002 | B15: Skill selector expands skill rows | C15: Exam detail page | D15: Toggle Listening/Reading/Writing/Speaking checkboxes | E15: Selected count, skill rows with part info, duration panel update | F15: Passed | G15: 46127 | H15: Nguyễn Trần Tấn Phát | I15: Passed | J15: 46134 | K15: Nguyễn Minh Khôi | L15: Passed | M15: 46141 | N15: Hoàng Văn Anh Nghĩa
A16: EXAM-DET-003 | B16: Full test cost displays correctly | C16: Config pricing loaded | D16: No skill selected | E16: Full-test cost displayed in bottom action bar | F16: Passed | G16: 46127 | H16: Nguyễn Minh Khôi | I16: Passed | J16: 46134 | K16: Hoàng Văn Anh Nghĩa | L16: Passed | M16: 46141 | N16: Nguyễn Nhật Phát

Sheet Exam Start
A2: Feature | B2: Start Exam Session
A3: Test requirement | B3: Full/custom start, coin, insufficient balance
A4: Number of TCs | B4: =COUNTA(A12:A997)
A5: Testing Round | B5: Passed | C5: Failed | D5: Pending | E5: N/A
A6: Round 1 | B6: =COUNTIF($F$12:$F$997,B$5) | C6: =COUNTIF($F$12:$F$997,C$5) | D6: =COUNTIF($F$12:$F$997,D$5) | E6: =COUNTIF($F$12:$F$997,E$5)
A7: Round 2 | B7: =COUNTIF($I$12:$I$997,B$5) | C7: =COUNTIF($I$12:$I$997,C$5) | D7: =COUNTIF($I$12:$I$997,D$5) | E7: =COUNTIF($I$12:$I$997,E$5)
A8: Round 3 | B8: =COUNTIF($L$12:$L$997,B$5) | C8: =COUNTIF($L$12:$L$997,C$5) | D8: =COUNTIF($L$12:$L$997,D$5) | E8: =COUNTIF($L$12:$L$997,E$5)
A10: Test Case ID | B10: Test Case Description | C10: Test Case Procedure | D10: Expected Results | E10: Pre-conditions | F10: Round 1 | G10: Test date | H10: Tester | I10: Round 2 | J10: Test date | K10: Tester | L10: Round 3 | M10: Test date | N10: Tester | O10: Note
A11: Exam
A12: EXAM-START-001 | B12: Start full test session charges coins | C12: Wallet balance ≥ 25 coins | D12: POST `exams/{examId}/sessions` mode=full | E12: 201, coins_charged=25, wallet debited, session_id returned | F12: Passed | G12: 46127 | H12: Hoàng Văn Anh Nghĩa | I12: Passed | J12: 46134 | K12: Nguyễn Nhật Phát | L12: Passed | M12: 46141 | N12: Nguyễn Trần Tấn Phát
A13: EXAM-START-002 | B13: Start custom session charges per skill | C13: Wallet balance ≥ per-skill cost | D13: POST mode=custom, selected_skills | E13: 201, coins_charged=selected×8, wallet debited | F13: Passed | G13: 46127 | H13: Nguyễn Nhật Phát | I13: Passed | J13: 46134 | K13: Nguyễn Trần Tấn Phát | L13: Passed | M13: 46141 | N13: Nguyễn Minh Khôi
A14: EXAM-START-003 | B14: Insufficient balance rejects session | C14: Wallet balance < cost | D14: POST exam session creation | E14: 422, session not created, balance unchanged | F14: Passed | G14: 46127 | H14: Nguyễn Trần Tấn Phát | I14: Passed | J14: 46134 | K14: Nguyễn Minh Khôi | L14: Passed | M14: 46141 | N14: Hoàng Văn Anh Nghĩa
A15: EXAM-START-004 | B15: Frontend shows top-up dialog when low balance | C15: Wallet low | D15: Click start exam | E15: TopUpDialog opens, session start blocked | F15: Passed | G15: 46127 | H15: Nguyễn Minh Khôi | I15: Passed | J15: 46134 | K15: Hoàng Văn Anh Nghĩa | L15: Passed | M15: 46141 | N15: Nguyễn Nhật Phát
A16: EXAM-START-005 | B16: Continue active same-exam session | C16: Active non-expired session exists | D16: Click continue on exam card/detail | E16: Navigate to existing /phong-thi/{sessionId} | F16: Passed | G16: 46127 | H16: Hoàng Văn Anh Nghĩa | I16: Passed | J16: 46134 | K16: Nguyễn Nhật Phát | L16: Passed | M16: 46141 | N16: Nguyễn Trần Tấn Phát
A17: EXAM-DC-001 | B17: Device check shows exam structure and media tests | C17: Session includes Listening and Speaking | D17: Enter exam room before start | E17: Structure, duration, audio test, microphone test, notes, start button | F17: Passed | G17: 46127 | H17: Nguyễn Nhật Phát | I17: Passed | J17: 46134 | K17: Nguyễn Trần Tấn Phát | L17: Passed | M17: 46141 | N17: Nguyễn Minh Khôi

Sheet Exam Draft
A2: Feature | B2: Draft Autosave
A3: Test requirement | B3: Save, autosave debounce, resume from draft
A4: Number of TCs | B4: =COUNTA(A12:A997)
A5: Testing Round | B5: Passed | C5: Failed | D5: Pending | E5: N/A
A6: Round 1 | B6: =COUNTIF($F$12:$F$997,B$5) | C6: =COUNTIF($F$12:$F$997,C$5) | D6: =COUNTIF($F$12:$F$997,D$5) | E6: =COUNTIF($F$12:$F$997,E$5)
A7: Round 2 | B7: =COUNTIF($I$12:$I$997,B$5) | C7: =COUNTIF($I$12:$I$997,C$5) | D7: =COUNTIF($I$12:$I$997,D$5) | E7: =COUNTIF($I$12:$I$997,E$5)
A8: Round 3 | B8: =COUNTIF($L$12:$L$997,B$5) | C8: =COUNTIF($L$12:$L$997,C$5) | D8: =COUNTIF($L$12:$L$997,D$5) | E8: =COUNTIF($L$12:$L$997,E$5)
A10: Test Case ID | B10: Test Case Description | C10: Test Case Procedure | D10: Expected Results | E10: Pre-conditions | F10: Round 1 | G10: Test date | H10: Tester | I10: Round 2 | J10: Test date | K10: Tester | L10: Round 3 | M10: Test date | N10: Tester | O10: Note
A11: Exam
A12: EXAM-DRAFT-001 | B12: Save exam draft | C12: Active session, answers exist | D12: PUT `exam-sessions/{id}/draft` | E12: 200, draft saved with skill_idx, mcq_answers, writing_answers, speaking_marks | F12: Passed | G12: 46127 | H12: Nguyễn Nhật Phát | I12: Passed | J12: 46134 | K12: Nguyễn Trần Tấn Phát | L12: Passed | M12: 46141 | N12: Nguyễn Minh Khôi
A13: EXAM-DRAFT-003 | B13: Draft autosave debounce in frontend | C13: Active exam, answers change | D13: Answer MCQ, write text, wait debounce 5s | E13: PUT draft endpoint called | F13: Passed | G13: 46127 | H13: Nguyễn Trần Tấn Phát | I13: Passed | J13: 46134 | K13: Nguyễn Minh Khôi | L13: Passed | M13: 46141 | N13: Hoàng Văn Anh Nghĩa
A14: EXAM-DRAFT-004 | B14: Resume active draft skips device check | C14: Active session with draft | D14: Reopen exam room URL | E14: Active phase opens directly with restored skill/answers | F14: Passed | G14: 46127 | H14: Nguyễn Minh Khôi | I14: Passed | J14: 46134 | K14: Hoàng Văn Anh Nghĩa | L14: Passed | M14: 46141 | N14: Nguyễn Nhật Phát

Sheet Exam Panels
A2: Feature | B2: Exam Room Panels
A3: Test requirement | B3: L/R/W/S panels, device check
A4: Number of TCs | B4: =COUNTA(A12:A997)
A5: Testing Round | B5: Passed | C5: Failed | D5: Pending | E5: N/A
A6: Round 1 | B6: =COUNTIF($F$12:$F$997,B$5) | C6: =COUNTIF($F$12:$F$997,C$5) | D6: =COUNTIF($F$12:$F$997,D$5) | E6: =COUNTIF($F$12:$F$997,E$5)
A7: Round 2 | B7: =COUNTIF($I$12:$I$997,B$5) | C7: =COUNTIF($I$12:$I$997,C$5) | D7: =COUNTIF($I$12:$I$997,D$5) | E7: =COUNTIF($I$12:$I$997,E$5)
A8: Round 3 | B8: =COUNTIF($L$12:$L$997,B$5) | C8: =COUNTIF($L$12:$L$997,C$5) | D8: =COUNTIF($L$12:$L$997,D$5) | E8: =COUNTIF($L$12:$L$997,E$5)
A10: Test Case ID | B10: Test Case Description | C10: Test Case Procedure | D10: Expected Results | E10: Pre-conditions | F10: Round 1 | G10: Test date | H10: Tester | I10: Round 2 | J10: Test date | K10: Tester | L10: Round 3 | M10: Test date | N10: Tester | O10: Note
A11: Exam
A12: EXAM-PANEL-001 | B12: Listening readiness modal | C12: Listening active | D12: Click audio | E12: Modal shown, confirm → audio plays | F12: Passed | G12: 46127 | H12: Nguyễn Trần Tấn Phát | I12: Passed | J12: 46134 | K12: Nguyễn Minh Khôi | L12: Passed | M12: 46141 | N12: Hoàng Văn Anh Nghĩa
A13: EXAM-PANEL-004 | B13: Reading passage/question split layout | C13: Reading passage + items | D13: Open reading panel | E13: Passage on one side, questions on other, navigation works | F13: Passed | G13: 46127 | H13: Nguyễn Minh Khôi | I13: Passed | J13: 46134 | K13: Hoàng Văn Anh Nghĩa | L13: Passed | M13: 46141 | N13: Nguyễn Nhật Phát
A14: EXAM-PANEL-006 | B14: Writing editor with word count | C14: Writing tasks exist | D14: Type text | E14: Word count, min_word progress, task tabs | F14: Passed | G14: 46127 | H14: Hoàng Văn Anh Nghĩa | I14: Passed | J14: 46134 | K14: Nguyễn Nhật Phát | L14: Passed | M14: 46141 | N14: Nguyễn Trần Tấn Phát
A15: EXAM-PANEL-008 | B15: Speaking panel with recording | C15: Microphone permission granted | D15: Record part, stop, playback, confirm | E15: Recording states, waveform, playback, done marks | F15: Passed | G15: 46127 | H15: Nguyễn Nhật Phát | I15: Passed | J15: 46134 | K15: Nguyễn Trần Tấn Phát | L15: Passed | M15: 46141 | N15: Nguyễn Minh Khôi
A16: EXAM-PANEL-009 | B16: Speaking microphone denied | C16: Microphone blocked | D16: Attempt recording | E16: Error message shown, recording cannot proceed | F16: Passed | G16: 46127 | H16: Nguyễn Trần Tấn Phát | I16: Passed | J16: 46134 | K16: Nguyễn Minh Khôi | L16: Passed | M16: 46141 | N16: Hoàng Văn Anh Nghĩa

Sheet Exam Submit
A2: Feature | B2: Transition & Submit
A3: Test requirement | B3: Next skill, confirm, submit, auto-submit, scoring
A4: Number of TCs | B4: =COUNTA(A12:A997)
A5: Testing Round | B5: Passed | C5: Failed | D5: Pending | E5: N/A
A6: Round 1 | B6: =COUNTIF($F$12:$F$997,B$5) | C6: =COUNTIF($F$12:$F$997,C$5) | D6: =COUNTIF($F$12:$F$997,D$5) | E6: =COUNTIF($F$12:$F$997,E$5)
A7: Round 2 | B7: =COUNTIF($I$12:$I$997,B$5) | C7: =COUNTIF($I$12:$I$997,C$5) | D7: =COUNTIF($I$12:$I$997,D$5) | E7: =COUNTIF($I$12:$I$997,E$5)
A8: Round 3 | B8: =COUNTIF($L$12:$L$997,B$5) | C8: =COUNTIF($L$12:$L$997,C$5) | D8: =COUNTIF($L$12:$L$997,D$5) | E8: =COUNTIF($L$12:$L$997,E$5)
A10: Test Case ID | B10: Test Case Description | C10: Test Case Procedure | D10: Expected Results | E10: Pre-conditions | F10: Round 1 | G10: Test date | H10: Tester | I10: Round 2 | J10: Test date | K10: Tester | L10: Round 3 | M10: Test date | N10: Tester | O10: Note
A11: Exam
A12: EXAM-TRANS-001 | B12: Next skill confirm dialog | C12: Current skill has answers | D12: Click next | E12: Confirm dialog with warning counts (unanswered, under-minimum, incomplete parts) | F12: Passed | G12: 46127 | H12: Nguyễn Minh Khôi | I12: Passed | J12: 46134 | K12: Hoàng Văn Anh Nghĩa | L12: Passed | M12: 46141 | N12: Nguyễn Nhật Phát
A13: EXAM-TRANS-002 | B13: Next skill locks previous skill | C13: Confirm next | D13: Transition to next skill | E13: Previous skill inaccessible | F13: Passed | G13: 46127 | H13: Hoàng Văn Anh Nghĩa | I13: Passed | J13: 46134 | K13: Nguyễn Nhật Phát | L13: Passed | M13: 46141 | N13: Nguyễn Trần Tấn Phát
A14: EXAM-SUBMIT-001 | B14: Manual submit posts answers and invalidates caches | C14: All selected skills completed | D14: Click submit, confirm | E14: POST submit called; exam, session, streak, overview, course, booking caches invalidated; result screen shown | F14: Passed | G14: 46127 | H14: Nguyễn Nhật Phát | I14: Passed | J14: 46134 | K14: Nguyễn Trần Tấn Phát | L14: Passed | M14: 46141 | N14: Nguyễn Minh Khôi
A15: EXAM-SUBMIT-002 | B15: Auto-submit after timer expires | C15: Timer reaches 0 | D15: Wait for expiry | E15: Expired overlay appears, submit triggered automatically | F15: Passed | G15: 46127 | H15: Nguyễn Trần Tấn Phát | I15: Passed | J15: 46134 | K15: Nguyễn Minh Khôi | L15: Passed | M15: 46141 | N15: Hoàng Văn Anh Nghĩa
A16: EXAM-SUBMIT-003 | B16: Submit with correct MCQ scoring | C16: MCQ answers mixed correct/wrong | D16: Submit | E16: Score calculated, correct/incorrect per item | F16: Passed | G16: 46127 | H16: Nguyễn Minh Khôi | I16: Passed | J16: 46134 | K16: Hoàng Văn Anh Nghĩa | L16: Passed | M16: 46141 | N16: Nguyễn Nhật Phát

Sheet Exam Result
A2: Feature | B2: Exam Result
A3: Test requirement | B3: Result summary, feedback, polling, detail page
A4: Number of TCs | B4: =COUNTA(A12:A997)
A5: Testing Round | B5: Passed | C5: Failed | D5: Pending | E5: N/A
A6: Round 1 | B6: =COUNTIF($F$12:$F$997,B$5) | C6: =COUNTIF($F$12:$F$997,C$5) | D6: =COUNTIF($F$12:$F$997,D$5) | E6: =COUNTIF($F$12:$F$997,E$5)
A7: Round 2 | B7: =COUNTIF($I$12:$I$997,B$5) | C7: =COUNTIF($I$12:$I$997,C$5) | D7: =COUNTIF($I$12:$I$997,D$5) | E7: =COUNTIF($I$12:$I$997,E$5)
A8: Round 3 | B8: =COUNTIF($L$12:$L$997,B$5) | C8: =COUNTIF($L$12:$L$997,C$5) | D8: =COUNTIF($L$12:$L$997,D$5) | E8: =COUNTIF($L$12:$L$997,E$5)
A10: Test Case ID | B10: Test Case Description | C10: Test Case Procedure | D10: Expected Results | E10: Pre-conditions | F10: Round 1 | G10: Test date | H10: Tester | I10: Round 2 | J10: Test date | K10: Tester | L10: Round 3 | M10: Test date | N10: Tester | O10: Note
A11: Exam
A12: EXAM-RESULT-001 | B12: Submit result summary displays MCQ score | C12: Session submitted | D12: Open result page | E12: Score circle, skill rows, pending AI badges for Writing/Speaking | F12: Passed | G12: 46127 | H12: Hoàng Văn Anh Nghĩa | I12: Passed | J12: 46134 | K12: Nguyễn Nhật Phát | L12: Passed | M12: 46141 | N12: Nguyễn Trần Tấn Phát
A13: EXAM-RESULT-002 | B13: Writing feedback displays after grading | C13: Writing graded | D13: Refresh result page | E13: Overall band, rubric dimensions, strengths, improvements, rewrites | F13: Passed | G13: 46127 | H13: Nguyễn Nhật Phát | I13: Passed | J13: 46134 | K13: Nguyễn Trần Tấn Phát | L13: Passed | M13: 46141 | N13: Nguyễn Minh Khôi
A14: EXAM-RESULT-004 | B14: Result polling while AI grading pending | C14: Writing/Speaking feedback overall_band is null | D14: Open result page | E14: Query polls every 5 seconds until all feedback has band | F14: Passed | G14: 46127 | H14: Nguyễn Trần Tấn Phát | I14: Passed | J14: 46134 | K14: Nguyễn Minh Khôi | L14: Passed | M14: 46141 | N14: Hoàng Văn Anh Nghĩa
A15: EXAM-RESULT-005 | B15: Result detail page shows MCQ answer grid | C15: Session submitted | D15: Click detail link | E15: Selected vs correct answers displayed, per-question accuracy | F15: Passed | G15: 46127 | H15: Nguyễn Minh Khôi | I15: Passed | J15: 46134 | K15: Hoàng Văn Anh Nghĩa | L15: Passed | M15: 46141 | N15: Nguyễn Nhật Phát

Sheet Wallet Balance
A2: Feature | B2: Wallet Balance
A3: Test requirement | B3: Balance endpoint, header display
A4: Number of TCs | B4: =COUNTA(A12:A997)
A5: Testing Round | B5: Passed | C5: Failed | D5: Pending | E5: N/A
A6: Round 1 | B6: =COUNTIF($F$12:$F$997,B$5) | C6: =COUNTIF($F$12:$F$997,C$5) | D6: =COUNTIF($F$12:$F$997,D$5) | E6: =COUNTIF($F$12:$F$997,E$5)
A7: Round 2 | B7: =COUNTIF($I$12:$I$997,B$5) | C7: =COUNTIF($I$12:$I$997,C$5) | D7: =COUNTIF($I$12:$I$997,D$5) | E7: =COUNTIF($I$12:$I$997,E$5)
A8: Round 3 | B8: =COUNTIF($L$12:$L$997,B$5) | C8: =COUNTIF($L$12:$L$997,C$5) | D8: =COUNTIF($L$12:$L$997,D$5) | E8: =COUNTIF($L$12:$L$997,E$5)
A10: Test Case ID | B10: Test Case Description | C10: Test Case Procedure | D10: Expected Results | E10: Pre-conditions | F10: Round 1 | G10: Test date | H10: Tester | I10: Round 2 | J10: Test date | K10: Tester | L10: Round 3 | M10: Test date | N10: Tester | O10: Note
A11: Wallet
A12: WALL-BAL-001 | B12: Get wallet balance | C12: Authenticated learner with active profile | D12: GET `wallet/balance` | E12: 200, balance returned (new learner: 100 coin) | F12: Passed | G12: 46127 | H12: Nguyễn Nhật Phát | I12: Passed | J12: 46134 | K12: Nguyễn Trần Tấn Phát | L12: Passed | M12: 46141 | N12: Nguyễn Minh Khôi
A13: WALL-BAL-003 | B13: Frontend header displays wallet balance | C13: Authenticated, balance > 0 | D13: Open dashboard or any _app route | E13: Coin pill in header shows formatted balance | F13: Passed | G13: 46127 | H13: Nguyễn Trần Tấn Phát | I13: Passed | J13: 46134 | K13: Nguyễn Minh Khôi | L13: Passed | M13: 46141 | N13: Hoàng Văn Anh Nghĩa

Sheet Top-up
A2: Feature | B2: Top-up & Payment
A3: Test requirement | B3: Package list, order, confirm, redirect
A4: Number of TCs | B4: =COUNTA(A12:A997)
A5: Testing Round | B5: Passed | C5: Failed | D5: Pending | E5: N/A
A6: Round 1 | B6: =COUNTIF($F$12:$F$997,B$5) | C6: =COUNTIF($F$12:$F$997,C$5) | D6: =COUNTIF($F$12:$F$997,D$5) | E6: =COUNTIF($F$12:$F$997,E$5)
A7: Round 2 | B7: =COUNTIF($I$12:$I$997,B$5) | C7: =COUNTIF($I$12:$I$997,C$5) | D7: =COUNTIF($I$12:$I$997,D$5) | E7: =COUNTIF($I$12:$I$997,E$5)
A8: Round 3 | B8: =COUNTIF($L$12:$L$997,B$5) | C8: =COUNTIF($L$12:$L$997,C$5) | D8: =COUNTIF($L$12:$L$997,D$5) | E8: =COUNTIF($L$12:$L$997,E$5)
A10: Test Case ID | B10: Test Case Description | C10: Test Case Procedure | D10: Expected Results | E10: Pre-conditions | F10: Round 1 | G10: Test date | H10: Tester | I10: Round 2 | J10: Test date | K10: Tester | L10: Round 3 | M10: Test date | N10: Tester | O10: Note
A11: Wallet
A12: WALL-TOP-001 | B12: List active top-up packages only | C12: Active and inactive packages exist | D12: GET `wallet/topup-packages` | E12: 200, only active packages, sorted by display_order | F12: Passed | G12: 46127 | H12: Nguyễn Trần Tấn Phát | I12: Passed | J12: 46134 | K12: Nguyễn Minh Khôi | L12: Passed | M12: 46141 | N12: Hoàng Văn Anh Nghĩa
A13: WALL-TOP-002 | B13: Frontend top-up dialog loads packages | C13: Authenticated, packages exist | D13: Click coin pill in header | E13: TopUpDialog opens, package list displayed with price/coin/bonus info | F13: Passed | G13: 46127 | H13: Nguyễn Minh Khôi | I13: Passed | J13: 46134 | K13: Hoàng Văn Anh Nghĩa | L13: Passed | M13: 46141 | N13: Nguyễn Nhật Phát
A14: WALL-PAY-001 | B14: Create top-up order | C14: Package exists, authenticated | D14: POST `wallet/topup` with package_id, provider=payos | E14: 201, order with status=pending, order_code, amount_vnd, coins_to_credit | F14: Passed | G14: 46127 | H14: Hoàng Văn Anh Nghĩa | I14: Passed | J14: 46134 | K14: Nguyễn Nhật Phát | L14: Passed | M14: 46141 | N14: Nguyễn Trần Tấn Phát
A15: WALL-PAY-002 | B15: Confirm top-up credits coins | C15: Pending order, payment callback or manual confirm | D15: Simulate payment callback or TopupService.confirmByOrderCode | E15: Order status → paid, coins credited to wallet, transaction created | F15: Passed | G15: 46127 | H15: Nguyễn Nhật Phát | I15: Passed | J15: 46134 | K15: Nguyễn Trần Tấn Phát | L15: Passed | M15: 46141 | N15: Nguyễn Minh Khôi
A16: WALL-PAY-004 | B16: Frontend redirects to payment URL | C16: Top-up order created with payment_url | D16: Click payment action on selected package | E16: Browser navigates to payment_url | F16: Passed | G16: 46127 | H16: Nguyễn Trần Tấn Phát | I16: Passed | J16: 46134 | K16: Nguyễn Minh Khôi | L16: Passed | M16: 46141 | N16: Hoàng Văn Anh Nghĩa

Sheet Promo Redeem
A2: Feature | B2: Promo Redemption
A3: Test requirement | B3: Valid/invalid redeem, frontend, error
A4: Number of TCs | B4: =COUNTA(A12:A997)
A5: Testing Round | B5: Passed | C5: Failed | D5: Pending | E5: N/A
A6: Round 1 | B6: =COUNTIF($F$12:$F$997,B$5) | C6: =COUNTIF($F$12:$F$997,C$5) | D6: =COUNTIF($F$12:$F$997,D$5) | E6: =COUNTIF($F$12:$F$997,E$5)
A7: Round 2 | B7: =COUNTIF($I$12:$I$997,B$5) | C7: =COUNTIF($I$12:$I$997,C$5) | D7: =COUNTIF($I$12:$I$997,D$5) | E7: =COUNTIF($I$12:$I$997,E$5)
A8: Round 3 | B8: =COUNTIF($L$12:$L$997,B$5) | C8: =COUNTIF($L$12:$L$997,C$5) | D8: =COUNTIF($L$12:$L$997,D$5) | E8: =COUNTIF($L$12:$L$997,E$5)
A10: Test Case ID | B10: Test Case Description | C10: Test Case Procedure | D10: Expected Results | E10: Pre-conditions | F10: Round 1 | G10: Test date | H10: Tester | I10: Round 2 | J10: Test date | K10: Tester | L10: Round 3 | M10: Test date | N10: Tester | O10: Note
A11: Wallet
A12: WALL-PROMO-001 | B12: Redeem valid promo code | C12: Valid promo code exists, learner has active profile | D12: POST `wallet/promo-redeem` with code | E12: 200, coins granted, balance updated | F12: Passed | G12: 46127 | H12: Nguyễn Minh Khôi | I12: Passed | J12: 46134 | K12: Hoàng Văn Anh Nghĩa | L12: Passed | M12: 46141 | N12: Nguyễn Nhật Phát
A13: WALL-PROMO-002 | B13: Redeem invalid promo code | C13: Code does not exist | D13: POST promo redeem with invalid code | E13: 422, error message, balance unchanged | F13: Passed | G13: 46127 | H13: Hoàng Văn Anh Nghĩa | I13: Passed | J13: 46134 | K13: Nguyễn Nhật Phát | L13: Passed | M13: 46141 | N13: Nguyễn Trần Tấn Phát
A14: WALL-PROMO-005 | B14: Frontend promo redeem card on profile | C14: Authenticated, profile page | D14: Enter code in PromoRedeemCard, submit | E14: On success: code cleared, success popup, balance invalidated | F14: Passed | G14: 46127 | H14: Nguyễn Nhật Phát | I14: Passed | J14: 46134 | K14: Nguyễn Trần Tấn Phát | L14: Passed | M14: 46141 | N14: Nguyễn Minh Khôi
A15: WALL-PROMO-006 | B15: Frontend promo redeem field error | C15: Invalid code submitted | D15: Submit code | E15: Field error displayed, success popup not shown | F15: Passed | G15: 46127 | H15: Nguyễn Trần Tấn Phát | I15: Passed | J15: 46134 | K15: Nguyễn Minh Khôi | L15: Passed | M15: 46141 | N15: Hoàng Văn Anh Nghĩa

Sheet Dashboard
A2: Feature | B2: Dashboard & Progress
A3: Test requirement | B3: Overview, spider chart, streak, learning path
A4: Number of TCs | B4: =COUNTA(A12:A997)
A5: Testing Round | B5: Passed | C5: Failed | D5: Pending | E5: N/A
A6: Round 1 | B6: =COUNTIF($F$12:$F$997,B$5) | C6: =COUNTIF($F$12:$F$997,C$5) | D6: =COUNTIF($F$12:$F$997,D$5) | E6: =COUNTIF($F$12:$F$997,E$5)
A7: Round 2 | B7: =COUNTIF($I$12:$I$997,B$5) | C7: =COUNTIF($I$12:$I$997,C$5) | D7: =COUNTIF($I$12:$I$997,D$5) | E7: =COUNTIF($I$12:$I$997,E$5)
A8: Round 3 | B8: =COUNTIF($L$12:$L$997,B$5) | C8: =COUNTIF($L$12:$L$997,C$5) | D8: =COUNTIF($L$12:$L$997,D$5) | E8: =COUNTIF($L$12:$L$997,E$5)
A10: Test Case ID | B10: Test Case Description | C10: Test Case Procedure | D10: Expected Results | E10: Pre-conditions | F10: Round 1 | G10: Test date | H10: Tester | I10: Round 2 | J10: Test date | K10: Tester | L10: Round 3 | M10: Test date | N10: Tester | O10: Note
A11: Progress
A12: DASH-OV-001 | B12: Overview returns profile/skill/streak/progress | C12: Authenticated learner with data | D12: GET `overview` | E12: 200, profile info, skill scores, streak data, progress | F12: Passed | G12: 46127 | H12: Hoàng Văn Anh Nghĩa | I12: Passed | J12: 46134 | K12: Nguyễn Nhật Phát | L12: Passed | M12: 46141 | N12: Nguyễn Trần Tấn Phát
A13: DASH-OV-003 | B13: Frontend dashboard renders overview cards | C13: Authenticated, some data | D13: Open `/dashboard` | E13: Overview cards, skill section, next action, recent activity | F13: Passed | G13: 46127 | H13: Nguyễn Nhật Phát | I13: Passed | J13: 46134 | K13: Nguyễn Trần Tấn Phát | L13: Passed | M13: 46141 | N13: Nguyễn Minh Khôi
A14: DASH-PROG-002 | B14: Spider chart hidden when fewer than 5 graded exams | C14: Exam count < 5 | D14: Open dashboard | E14: Chart hidden, message shown | F14: Passed | G14: 46127 | H14: Nguyễn Trần Tấn Phát | I14: Passed | J14: 46134 | K14: Nguyễn Minh Khôi | L14: Passed | M14: 46141 | N14: Hoàng Văn Anh Nghĩa
A15: DASH-PROG-003 | B15: Spider chart shows when enough graded exams | C15: 5+ graded full tests | D15: Open dashboard | E15: 4-axis spider chart with L/R/W/S bands | F15: Passed | G15: 46127 | H15: Nguyễn Minh Khôi | I15: Passed | J15: 46134 | K15: Hoàng Văn Anh Nghĩa | L15: Passed | M15: 46141 | N15: Nguyễn Nhật Phát
A16: DASH-STK-001 | B16: Streak endpoint shows current state | C16: Authenticated, activity today | D16: GET `streak` | E16: 200, current streak, today_active, milestones | F16: Passed | G16: 46127 | H16: Hoàng Văn Anh Nghĩa | I16: Passed | J16: 46134 | K16: Nguyễn Nhật Phát | L16: Passed | M16: 46141 | N16: Nguyễn Trần Tấn Phát
A17: DASH-STK-002 | B17: Streak increases after full-test submission | C17: Learner submits full-test exam today | D17: Submit exam, check streak | E17: Streak increments (if first full-test today), today_active=true | F17: Passed | G17: 46127 | H17: Nguyễn Nhật Phát | I17: Passed | J17: 46134 | K17: Nguyễn Trần Tấn Phát | L17: Passed | M17: 46141 | N17: Nguyễn Minh Khôi
A18: DASH-STK-003 | B18: Claim streak milestone grants coins | C18: Streak days reach milestone threshold | D18: POST `streak/milestones/{days}/claim` | E18: 200, coins granted, wallet updated, milestone marked claimed | F18: Passed | G18: 46127 | H18: Nguyễn Trần Tấn Phát | I18: Passed | J18: 46134 | K18: Nguyễn Minh Khôi | L18: Passed | M18: 46141 | N18: Hoàng Văn Anh Nghĩa
A19: DASH-STK-005 | B19: Frontend streak dialog | C19: Authenticated with streak data | D19: Open streak dialog from dashboard | E19: Current streak, milestones progress bar, chest rewards, claim buttons | F19: Passed | G19: 46127 | H19: Nguyễn Minh Khôi | I19: Passed | J19: 46134 | K19: Hoàng Văn Anh Nghĩa | L19: Passed | M19: 46141 | N19: Nguyễn Nhật Phát
A20: DASH-LP-001 | B20: Learning path returns weak skill recommendations | C20: Learner has exam results showing skill gaps | D20: GET `learning-path` | E20: 200, recommended skills with band/coverage data | F20: Passed | G20: 46127 | H20: Hoàng Văn Anh Nghĩa | I20: Passed | J20: 46134 | K20: Nguyễn Nhật Phát | L20: Passed | M20: 46141 | N20: Nguyễn Trần Tấn Phát
A21: DASH-LP-004 | B21: Frontend recommendation section | C21: Weak skills detected | D21: Open practice or dashboard | E21: Recommendation cards with band, coverage, suggested exercises | F21: Passed | G21: 46127 | H21: Nguyễn Nhật Phát | I21: Passed | J21: 46134 | K21: Nguyễn Trần Tấn Phát | L21: Passed | M21: 46141 | N21: Nguyễn Minh Khôi

Sheet Course Enroll
A2: Feature | B2: Course Enrollment
A3: Test requirement | B3: List, enrollment order, frontend flow
A4: Number of TCs | B4: =COUNTA(A12:A997)
A5: Testing Round | B5: Passed | C5: Failed | D5: Pending | E5: N/A
A6: Round 1 | B6: =COUNTIF($F$12:$F$997,B$5) | C6: =COUNTIF($F$12:$F$997,C$5) | D6: =COUNTIF($F$12:$F$997,D$5) | E6: =COUNTIF($F$12:$F$997,E$5)
A7: Round 2 | B7: =COUNTIF($I$12:$I$997,B$5) | C7: =COUNTIF($I$12:$I$997,C$5) | D7: =COUNTIF($I$12:$I$997,D$5) | E7: =COUNTIF($I$12:$I$997,E$5)
A8: Round 3 | B8: =COUNTIF($L$12:$L$997,B$5) | C8: =COUNTIF($L$12:$L$997,C$5) | D8: =COUNTIF($L$12:$L$997,D$5) | E8: =COUNTIF($L$12:$L$997,E$5)
A10: Test Case ID | B10: Test Case Description | C10: Test Case Procedure | D10: Expected Results | E10: Pre-conditions | F10: Round 1 | G10: Test date | H10: Tester | I10: Round 2 | J10: Test date | K10: Tester | L10: Round 3 | M10: Test date | N10: Tester | O10: Note
A11: Course
A12: COURSE-EN-001 | B12: List available courses | C12: Published courses exist | D12: GET `courses` | E12: 200, course list with title, teacher, price, dates | F12: Passed | G12: 46127 | H12: Nguyễn Nhật Phát | I12: Passed | J12: 46134 | K12: Nguyễn Trần Tấn Phát | L12: Passed | M12: 46141 | N12: Nguyễn Minh Khôi
A13: COURSE-EN-003 | B13: Create enrollment order | C13: Course available, wallet enough | D13: POST `courses/{course}/enrollment-orders` | E13: 201, enrollment order created, coins deducted | F13: Passed | G13: 46127 | H13: Nguyễn Trần Tấn Phát | I13: Passed | J13: 46134 | K13: Nguyễn Minh Khôi | L13: Passed | M13: 46141 | N13: Hoàng Văn Anh Nghĩa
A14: COURSE-EN-005 | B14: Course enrollment frontend flow | C14: Course available, sufficient coins | D14: Open course detail, click enroll | E14: EnrollDialog, coin deduction display, success confirmation | F14: Passed | G14: 46127 | H14: Nguyễn Minh Khôi | I14: Passed | J14: 46134 | K14: Hoàng Văn Anh Nghĩa | L14: Passed | M14: 46141 | N14: Nguyễn Nhật Phát

Sheet Booking
A2: Feature | B2: Booking & Notification
A3: Test requirement | B3: Book slot, coin, limit, commitment, notifications
A4: Number of TCs | B4: =COUNTA(A12:A997)
A5: Testing Round | B5: Passed | C5: Failed | D5: Pending | E5: N/A
A6: Round 1 | B6: =COUNTIF($F$12:$F$997,B$5) | C6: =COUNTIF($F$12:$F$997,C$5) | D6: =COUNTIF($F$12:$F$997,D$5) | E6: =COUNTIF($F$12:$F$997,E$5)
A7: Round 2 | B7: =COUNTIF($I$12:$I$997,B$5) | C7: =COUNTIF($I$12:$I$997,C$5) | D7: =COUNTIF($I$12:$I$997,D$5) | E7: =COUNTIF($I$12:$I$997,E$5)
A8: Round 3 | B8: =COUNTIF($L$12:$L$997,B$5) | C8: =COUNTIF($L$12:$L$997,C$5) | D8: =COUNTIF($L$12:$L$997,D$5) | E8: =COUNTIF($L$12:$L$997,E$5)
A10: Test Case ID | B10: Test Case Description | C10: Test Case Procedure | D10: Expected Results | E10: Pre-conditions | F10: Round 1 | G10: Test date | H10: Tester | I10: Round 2 | J10: Test date | K10: Tester | L10: Round 3 | M10: Test date | N10: Tester | O10: Note
A11: Course
A12: COURSE-BK-002 | B12: Book a slot | C12: Available slot, enrolled, enough coins | D12: POST `courses/{course}/bookings` with slot_id | E12: 201, booking created, coins deducted | F12: Passed | G12: 46127 | H12: Nguyễn Trần Tấn Phát | I12: Passed | J12: 46134 | K12: Nguyễn Minh Khôi | L12: Passed | M12: 46141 | N12: Hoàng Văn Anh Nghĩa
A13: COURSE-BK-003 | B13: Booking cost deduction from wallet | C13: Wallet enough coins | D13: Book slot | E13: Wallet balance decreases by booking_coin_cost | F13: Passed | G13: 46127 | H13: Nguyễn Minh Khôi | I13: Passed | J13: 46134 | K13: Hoàng Văn Anh Nghĩa | L13: Passed | M13: 46141 | N13: Nguyễn Nhật Phát
A14: COURSE-BK-004 | B14: Cannot book beyond max slots | C14: At max_bookings_per_student | D14: Try to book additional slot | E14: 422, limit reached | F14: Passed | G14: 46127 | H14: Hoàng Văn Anh Nghĩa | I14: Passed | J14: 46134 | K14: Nguyễn Nhật Phát | L14: Passed | M14: 46141 | N14: Nguyễn Trần Tấn Phát
A15: COURSE-BK-010 | B15: Commitment gate blocks booking | C15: Commitment not met (not enough full-tests in window) | D15: Try to book | E15: Booking blocked, message explaining commitment | F15: Passed | G15: 46127 | H15: Nguyễn Nhật Phát | I15: Passed | J15: 46134 | K15: Nguyễn Trần Tấn Phát | L15: Passed | M15: 46141 | N15: Nguyễn Minh Khôi
A16: NOTIF-001 | B16: List notifications for learner | C16: Some notifications exist | D16: GET `notifications` | E16: 200, notification list with type, title, body, read status | F16: Passed | G16: 46127 | H16: Nguyễn Trần Tấn Phát | I16: Passed | J16: 46134 | K16: Nguyễn Minh Khôi | L16: Passed | M16: 46141 | N16: Hoàng Văn Anh Nghĩa
A17: NOTIF-007 | B17: Frontend notification bell | C17: Authenticated, notifications exist | D17: Click bell icon | E17: Dropdown with recent notifications, unread badge | F17: Passed | G17: 46127 | H17: Nguyễn Minh Khôi | I17: Passed | J17: 46134 | K17: Hoàng Văn Anh Nghĩa | L17: Passed | M17: 46141 | N17: Nguyễn Nhật Phát

Sheet Admin Dashboard
A2: Feature | B2: Admin Dashboard
A3: Test requirement | B3: Stats, alerts, role enforcement, frontend
A4: Number of TCs | B4: =COUNTA(A12:A997)
A5: Testing Round | B5: Passed | C5: Failed | D5: Pending | E5: N/A
A6: Round 1 | B6: =COUNTIF($F$12:$F$997,B$5) | C6: =COUNTIF($F$12:$F$997,C$5) | D6: =COUNTIF($F$12:$F$997,D$5) | E6: =COUNTIF($F$12:$F$997,E$5)
A7: Round 2 | B7: =COUNTIF($I$12:$I$997,B$5) | C7: =COUNTIF($I$12:$I$997,C$5) | D7: =COUNTIF($I$12:$I$997,D$5) | E7: =COUNTIF($I$12:$I$997,E$5)
A8: Round 3 | B8: =COUNTIF($L$12:$L$997,B$5) | C8: =COUNTIF($L$12:$L$997,C$5) | D8: =COUNTIF($L$12:$L$997,D$5) | E8: =COUNTIF($L$12:$L$997,E$5)
A10: Test Case ID | B10: Test Case Description | C10: Test Case Procedure | D10: Expected Results | E10: Pre-conditions | F10: Round 1 | G10: Test date | H10: Tester | I10: Round 2 | J10: Test date | K10: Tester | L10: Round 3 | M10: Test date | N10: Tester | O10: Note
A11: Admin
A12: ADM-DASH-001 | B12: Dashboard returns aggregate stats | C12: Admin authenticated, data seeded | D12: GET `admin/stats` | E12: 200, users_total, exams_total, exams_published, vocab_topics, grammar_points | F12: Passed | G12: 46127 | H12: Nguyễn Minh Khôi | I12: Passed | J12: 46134 | K12: Hoàng Văn Anh Nghĩa | L12: Passed | M12: 46141 | N12: Nguyễn Nhật Phát
A13: ADM-DASH-002 | B13: Dashboard alerts detects failed grading jobs | C13: Failed grading job exists | D13: GET `admin/alerts` | E13: 200, alert with type=error | F13: Passed | G13: 46127 | H13: Hoàng Văn Anh Nghĩa | I13: Passed | J13: 46134 | K13: Nguyễn Nhật Phát | L13: Passed | M13: 46141 | N13: Nguyễn Trần Tấn Phát
A14: ADM-DASH-005 | B14: Admin dashboard requires staff role | C14: Learner user | D14: GET `admin/stats` with learner token | E14: 403 Forbidden | F14: Passed | G14: 46127 | H14: Nguyễn Nhật Phát | I14: Passed | J14: 46134 | K14: Nguyễn Trần Tấn Phát | L14: Passed | M14: 46141 | N14: Nguyễn Minh Khôi
A15: ADM-DASH-007 | B15: Frontend admin dashboard renders all card sections | C15: Admin authenticated, data available | D15: Open admin dashboard | E15: Stats cards, revenue charts, wallet economy, content chart, grading throughput, alerts visible | F15: Passed | G15: 46127 | H15: Nguyễn Trần Tấn Phát | I15: Passed | J15: 46134 | K15: Nguyễn Minh Khôi | L15: Passed | M15: 46141 | N15: Hoàng Văn Anh Nghĩa

Sheet Admin Vocab Grammar
A2: Feature | B2: Admin Vocab & Grammar
A3: Test requirement | B3: Vocab/grammar CRUD, publish/unpublish, frontend
A4: Number of TCs | B4: =COUNTA(A12:A997)
A5: Testing Round | B5: Passed | C5: Failed | D5: Pending | E5: N/A
A6: Round 1 | B6: =COUNTIF($F$12:$F$997,B$5) | C6: =COUNTIF($F$12:$F$997,C$5) | D6: =COUNTIF($F$12:$F$997,D$5) | E6: =COUNTIF($F$12:$F$997,E$5)
A7: Round 2 | B7: =COUNTIF($I$12:$I$997,B$5) | C7: =COUNTIF($I$12:$I$997,C$5) | D7: =COUNTIF($I$12:$I$997,D$5) | E7: =COUNTIF($I$12:$I$997,E$5)
A8: Round 3 | B8: =COUNTIF($L$12:$L$997,B$5) | C8: =COUNTIF($L$12:$L$997,C$5) | D8: =COUNTIF($L$12:$L$997,D$5) | E8: =COUNTIF($L$12:$L$997,E$5)
A10: Test Case ID | B10: Test Case Description | C10: Test Case Procedure | D10: Expected Results | E10: Pre-conditions | F10: Round 1 | G10: Test date | H10: Tester | I10: Round 2 | J10: Test date | K10: Tester | L10: Round 3 | M10: Test date | N10: Tester | O10: Note
A11: Admin
A12: ADM-VOC-001 | B12: List vocabulary topics | C12: Admin authenticated, topics exist | D12: GET `admin/vocab/topics` | E12: 200, topic list with status, word count | F12: Passed | G12: 46127 | H12: Hoàng Văn Anh Nghĩa | I12: Passed | J12: 46134 | K12: Nguyễn Nhật Phát | L12: Passed | M12: 46141 | N12: Nguyễn Trần Tấn Phát
A13: ADM-VOC-002 | B13: Create vocabulary topic | C13: Admin authenticated | D13: POST `admin/vocab/topics` with title/level/order | E13: 201, topic created as draft | F13: Passed | G13: 46127 | H13: Nguyễn Nhật Phát | I13: Passed | J13: 46134 | K13: Nguyễn Trần Tấn Phát | L13: Passed | M13: 46141 | N13: Nguyễn Minh Khôi
A14: ADM-VOC-004 | B14: Publish vocabulary topic | C14: Draft topic with words + exercises | D14: POST `admin/vocab/topics/{id}/publish` | E14: 200, topic published, visible to learners | F14: Passed | G14: 46127 | H14: Nguyễn Trần Tấn Phát | I14: Passed | J14: 46134 | K14: Nguyễn Minh Khôi | L14: Passed | M14: 46141 | N14: Hoàng Văn Anh Nghĩa
A15: ADM-VOC-005 | B15: Unpublish vocabulary topic | C15: Published topic | D15: POST `admin/vocab/topics/{id}/unpublish` | E15: 200, topic hidden from learners | F15: Passed | G15: 46127 | H15: Nguyễn Minh Khôi | I15: Passed | J15: 46134 | K15: Hoàng Văn Anh Nghĩa | L15: Passed | M15: 46141 | N15: Nguyễn Nhật Phát
A16: ADM-VOC-015 | B16: Frontend admin vocab topic page | C16: Admin logged in | D16: Open vocab section | E16: Topic list, create/edit form, publish toggles, word and exercise tabs | F16: Passed | G16: 46127 | H16: Hoàng Văn Anh Nghĩa | I16: Passed | J16: 46134 | K16: Nguyễn Nhật Phát | L16: Passed | M16: 46141 | N16: Nguyễn Trần Tấn Phát
A17: ADM-GRAM-001 | B17: List grammar points | C17: Admin authenticated, points exist | D17: GET `admin/grammar/points` | E17: 200, point list with publish status | F17: Passed | G17: 46127 | H17: Nguyễn Nhật Phát | I17: Passed | J17: 46134 | K17: Nguyễn Trần Tấn Phát | L17: Passed | M17: 46141 | N17: Nguyễn Minh Khôi
A18: ADM-GRAM-002 | B18: Create grammar point | C18: Admin authenticated | D18: POST `admin/grammar/points` | E18: 201, point created as draft | F18: Passed | G18: 46127 | H18: Nguyễn Trần Tấn Phát | I18: Passed | J18: 46134 | K18: Nguyễn Minh Khôi | L18: Passed | M18: 46141 | N18: Hoàng Văn Anh Nghĩa
A19: ADM-GRAM-004 | B19: Publish grammar point | C19: Draft point with content | D19: POST `admin/grammar/points/{id}/publish` | E19: 200, point published | F19: Passed | G19: 46127 | H19: Nguyễn Minh Khôi | I19: Passed | J19: 46134 | K19: Hoàng Văn Anh Nghĩa | L19: Passed | M19: 46141 | N19: Nguyễn Nhật Phát
A20: ADM-GRAM-005 | B20: Unpublish grammar point | C20: Published point | D20: POST `admin/grammar/points/{id}/unpublish` | E20: 200, point hidden | F20: Passed | G20: 46127 | H20: Hoàng Văn Anh Nghĩa | I20: Passed | J20: 46134 | K20: Nguyễn Nhật Phát | L20: Passed | M20: 46141 | N20: Nguyễn Trần Tấn Phát
A21: ADM-GRAM-012 | B21: Frontend admin grammar point form | C21: Admin logged in | D21: Open grammar point detail | E21: Structures, examples, mistakes, tips, exercises tabs with CRUD forms | F21: Passed | G21: 46127 | H21: Nguyễn Nhật Phát | I21: Passed | J21: 46134 | K21: Nguyễn Trần Tấn Phát | L21: Passed | M21: 46141 | N21: Nguyễn Minh Khôi

Sheet Admin Settings
A2: Feature | B2: Admin Settings
A3: Test requirement | B3: System config, update, role enforcement
A4: Number of TCs | B4: =COUNTA(A12:A997)
A5: Testing Round | B5: Passed | C5: Failed | D5: Pending | E5: N/A
A6: Round 1 | B6: =COUNTIF($F$12:$F$997,B$5) | C6: =COUNTIF($F$12:$F$997,C$5) | D6: =COUNTIF($F$12:$F$997,D$5) | E6: =COUNTIF($F$12:$F$997,E$5)
A7: Round 2 | B7: =COUNTIF($I$12:$I$997,B$5) | C7: =COUNTIF($I$12:$I$997,C$5) | D7: =COUNTIF($I$12:$I$997,D$5) | E7: =COUNTIF($I$12:$I$997,E$5)
A8: Round 3 | B8: =COUNTIF($L$12:$L$997,B$5) | C8: =COUNTIF($L$12:$L$997,C$5) | D8: =COUNTIF($L$12:$L$997,D$5) | E8: =COUNTIF($L$12:$L$997,E$5)
A10: Test Case ID | B10: Test Case Description | C10: Test Case Procedure | D10: Expected Results | E10: Pre-conditions | F10: Round 1 | G10: Test date | H10: Tester | I10: Round 2 | J10: Test date | K10: Tester | L10: Round 3 | M10: Test date | N10: Tester | O10: Note
A11: Admin
A12: ADM-CONFIG-001 | B12: List system config | C12: Admin authenticated | D12: GET `admin/system-config` | E12: 200, config key-value list | F12: Passed | G12: 46127 | H12: Nguyễn Nhật Phát | I12: Passed | J12: 46134 | K12: Nguyễn Trần Tấn Phát | L12: Passed | M12: 46141 | N12: Nguyễn Minh Khôi
A13: ADM-CONFIG-003 | B13: Update system config | C13: Admin authenticated, valid value | D13: PATCH `admin/system-config/{key}` with valid value | E13: 200, value updated | F13: Passed | G13: 46127 | H13: Nguyễn Trần Tấn Phát | I13: Passed | J13: 46134 | K13: Nguyễn Minh Khôi | L13: Passed | M13: 46141 | N13: Hoàng Văn Anh Nghĩa
A14: ADM-CONFIG-004 | B14: System config admin-only (not staff) | C14: Staff user (not admin) | D14: GET `admin/system-config` | E14: 403 | F14: Passed | G14: 46127 | H14: Nguyễn Minh Khôi | I14: Passed | J14: 46134 | K14: Hoàng Văn Anh Nghĩa | L14: Passed | M14: 46141 | N14: Nguyễn Nhật Phát

Sheet Admin Exams
A2: Feature | B2: Admin Exam Mgmt
A3: Test requirement | B3: Exam CRUD, import, version, content editors
A4: Number of TCs | B4: =COUNTA(A12:A997)
A5: Testing Round | B5: Passed | C5: Failed | D5: Pending | E5: N/A
A6: Round 1 | B6: =COUNTIF($F$12:$F$997,B$5) | C6: =COUNTIF($F$12:$F$997,C$5) | D6: =COUNTIF($F$12:$F$997,D$5) | E6: =COUNTIF($F$12:$F$997,E$5)
A7: Round 2 | B7: =COUNTIF($I$12:$I$997,B$5) | C7: =COUNTIF($I$12:$I$997,C$5) | D7: =COUNTIF($I$12:$I$997,D$5) | E7: =COUNTIF($I$12:$I$997,E$5)
A8: Round 3 | B8: =COUNTIF($L$12:$L$997,B$5) | C8: =COUNTIF($L$12:$L$997,C$5) | D8: =COUNTIF($L$12:$L$997,D$5) | E8: =COUNTIF($L$12:$L$997,E$5)
A10: Test Case ID | B10: Test Case Description | C10: Test Case Procedure | D10: Expected Results | E10: Pre-conditions | F10: Round 1 | G10: Test date | H10: Tester | I10: Round 2 | J10: Test date | K10: Tester | L10: Round 3 | M10: Test date | N10: Tester | O10: Note
A11: Admin
A12: ADM-EXAM-001 | B12: List all exams | C12: Admin authenticated | D12: GET `admin/exams` | E12: 200, exam list with draft/published status | F12: Passed | G12: 46127 | H12: Nguyễn Trần Tấn Phát | I12: Passed | J12: 46134 | K12: Nguyễn Minh Khôi | L12: Passed | M12: 46141 | N12: Hoàng Văn Anh Nghĩa
A13: ADM-EXAM-002 | B13: Create exam | C13: Admin authenticated | D13: POST `admin/exams` with title/slug/duration | E13: 201, exam created as draft | F13: Passed | G13: 46127 | H13: Nguyễn Minh Khôi | I13: Passed | J13: 46134 | K13: Hoàng Văn Anh Nghĩa | L13: Passed | M13: 46141 | N13: Nguyễn Nhật Phát
A14: ADM-EXAM-003 | B14: Update exam | C14: Exam exists | D14: PATCH `admin/exams/{id}` | E14: 200, exam updated | F14: Passed | G14: 46127 | H14: Hoàng Văn Anh Nghĩa | I14: Passed | J14: 46134 | K14: Nguyễn Nhật Phát | L14: Passed | M14: 46141 | N14: Nguyễn Trần Tấn Phát
A15: ADM-EXAM-004 | B15: Publish exam | C15: Draft exam with complete version and content | D15: POST `admin/exams/{id}/publish` | E15: 200, exam visible to learners | F15: Passed | G15: 46127 | H15: Nguyễn Nhật Phát | I15: Passed | J15: 46134 | K15: Nguyễn Trần Tấn Phát | L15: Passed | M15: 46141 | N15: Nguyễn Minh Khôi
A16: ADM-EXAM-005 | B16: Unpublish exam | C16: Published exam | D16: POST `admin/exams/{id}/unpublish` | E16: 200, exam hidden | F16: Passed | G16: 46127 | H16: Nguyễn Trần Tấn Phát | I16: Passed | J16: 46134 | K16: Nguyễn Minh Khôi | L16: Passed | M16: 46141 | N16: Hoàng Văn Anh Nghĩa
A17: ADM-EXAM-007 | B17: Import exam | C17: Valid import payload | D17: POST `admin/exams/import` | E17: 201, exam created from import | F17: Passed | G17: 46127 | H17: Nguyễn Minh Khôi | I17: Passed | J17: 46134 | K17: Hoàng Văn Anh Nghĩa | L17: Passed | M17: 46141 | N17: Nguyễn Nhật Phát
A18: ADM-EXAM-008 | B18: Frontend admin exam list | C18: Admin logged in | D18: Open exams section | E18: Exam list, version selector, publish actions | F18: Passed | G18: 46127 | H18: Hoàng Văn Anh Nghĩa | I18: Passed | J18: 46134 | K18: Nguyễn Nhật Phát | L18: Passed | M18: 46141 | N18: Nguyễn Trần Tấn Phát
A19: ADM-EXAM-VER-001 | B19: List exam versions | C19: Exam has versions | D19: GET `admin/exams/{examId}/versions` | E19: 200, version list | F19: Passed | G19: 46127 | H19: Nguyễn Nhật Phát | I19: Passed | J19: 46134 | K19: Nguyễn Trần Tấn Phát | L19: Passed | M19: 46141 | N19: Nguyễn Minh Khôi
A20: ADM-EXAM-VER-003 | B20: Activate exam version | C20: Multiple versions | D20: POST activate | E20: Active version becomes the visible one | F20: Passed | G20: 46127 | H20: Nguyễn Trần Tấn Phát | I20: Passed | J20: 46134 | K20: Nguyễn Minh Khôi | L20: Passed | M20: 46141 | N20: Hoàng Văn Anh Nghĩa
A21: ADM-EXAM-VER-005 | B21: Frontend version selector | C21: Multiple versions | D21: Open exam, switch | E21: Active version highlighted | F21: Passed | G21: 46127 | H21: Nguyễn Minh Khôi | I21: Passed | J21: 46134 | K21: Hoàng Văn Anh Nghĩa | L21: Passed | M21: 46141 | N21: Nguyễn Nhật Phát
A22: ADM-EXAM-CON-001 | B22: Create listening section with items | C22: Version exists | D22: POST listening section + items | E22: 201, content created | F22: Passed | G22: 46127 | H22: Hoàng Văn Anh Nghĩa | I22: Passed | J22: 46134 | K22: Nguyễn Nhật Phát | L22: Passed | M22: 46141 | N22: Nguyễn Trần Tấn Phát
A23: ADM-EXAM-CON-003 | B23: Create reading passage with items | C23: Version exists | D23: POST reading passage + items | E23: 201, content created | F23: Passed | G23: 46127 | H23: Nguyễn Nhật Phát | I23: Passed | J23: 46134 | K23: Nguyễn Trần Tấn Phát | L23: Passed | M23: 46141 | N23: Nguyễn Minh Khôi
... A26: ADM-EXAM-CON-006 | B26: Frontend exam content editors (4 tabs) | C26: Version selected | D26: Open Listening/Reading/Writing/Speaking tabs | E26: Forms render, content editable | F26: Passed | G26: 46127 | H26: Hoàng Văn Anh Nghĩa | I26: Passed | J26: 46134 | K26: Nguyễn Nhật Phát | L26: Passed | M26: 46141 | N26: Nguyễn Trần Tấn Phát

Sheet Admin Practice
A2: Feature | B2: Admin Practice Content
A3: Test requirement | B3: L/R/W/S exercise CRUD, editors
A4: Number of TCs | B4: =COUNTA(A12:A997)
A5: Testing Round | B5: Passed | C5: Failed | D5: Pending | E5: N/A
A6: Round 1 | B6: =COUNTIF($F$12:$F$997,B$5) | C6: =COUNTIF($F$12:$F$997,C$5) | D6: =COUNTIF($F$12:$F$997,D$5) | E6: =COUNTIF($F$12:$F$997,E$5)
A7: Round 2 | B7: =COUNTIF($I$12:$I$997,B$5) | C7: =COUNTIF($I$12:$I$997,C$5) | D7: =COUNTIF($I$12:$I$997,D$5) | E7: =COUNTIF($I$12:$I$997,E$5)
A8: Round 3 | B8: =COUNTIF($L$12:$L$997,B$5) | C8: =COUNTIF($L$12:$L$997,C$5) | D8: =COUNTIF($L$12:$L$997,D$5) | E8: =COUNTIF($L$12:$L$997,E$5)
A10: Test Case ID | B10: Test Case Description | C10: Test Case Procedure | D10: Expected Results | E10: Pre-conditions | F10: Round 1 | G10: Test date | H10: Tester | I10: Round 2 | J10: Test date | K10: Tester | L10: Round 3 | M10: Test date | N10: Tester | O10: Note
A11: Admin
A12: ADM-PRAC-LIS-002 | B12: Create listening exercise | C12: Admin authenticated | D12: POST with title/level/audio_url/transcript | E12: 201 | F12: Passed | G12: 46127 | H12: Nguyễn Minh Khôi | I12: Passed | J12: 46134 | K12: Hoàng Văn Anh Nghĩa | L12: Passed | M12: 46141 | N12: Nguyễn Nhật Phát
A13: ADM-PRAC-LIS-005 | B13: Frontend listening exercise editor | C13: Admin logged in | D13: Open practice → listening | E13: Exercise list, form, questions tab | F13: Passed | G13: 46127 | H13: Hoàng Văn Anh Nghĩa | I13: Passed | J13: 46134 | K13: Nguyễn Nhật Phát | L13: Passed | M13: 46141 | N13: Nguyễn Trần Tấn Phát
A14: ADM-PRAC-REA-002 | B14: Create reading exercise | C14: Admin authenticated | D14: POST with title/level/passage | E14: 201 | F14: Passed | G14: 46127 | H14: Nguyễn Nhật Phát | I14: Passed | J14: 46134 | K14: Nguyễn Trần Tấn Phát | L14: Passed | M14: 46141 | N14: Nguyễn Minh Khôi
A15: ADM-PRAC-REA-004 | B15: Frontend reading exercise editor | C15: Admin logged in | D15: Open practice → reading | E15: Exercise form, questions tab | F15: Passed | G15: 46127 | H15: Nguyễn Trần Tấn Phát | I15: Passed | J15: 46134 | K15: Nguyễn Minh Khôi | L15: Passed | M15: 46141 | N15: Hoàng Văn Anh Nghĩa
A16: ADM-PRAC-WRI-002 | B16: Create writing prompt | C16: Admin authenticated | D16: POST with title/level/task_type/min_words | E16: 201 | F16: Passed | G16: 46127 | H16: Nguyễn Minh Khôi | I16: Passed | J16: 46134 | K16: Hoàng Văn Anh Nghĩa | L16: Passed | M16: 46141 | N16: Nguyễn Nhật Phát
A17: ADM-PRAC-WRI-004 | B17: Frontend writing prompt editor | C17: Admin logged in | D17: Open practice → writing | E17: Prompt form, markers tab | F17: Passed | G17: 46127 | H17: Hoàng Văn Anh Nghĩa | I17: Passed | J17: 46134 | K17: Nguyễn Nhật Phát | L17: Passed | M17: 46141 | N17: Nguyễn Trần Tấn Phát
A18: ADM-PRAC-SPK-004 | B18: Create speaking VSTEP task | C18: Admin authenticated | D18: POST with title/level/part/prompt/duration | E18: 201 | F18: Passed | G18: 46127 | H18: Nguyễn Nhật Phát | I18: Passed | J18: 46134 | K18: Nguyễn Trần Tấn Phát | L18: Passed | M18: 46141 | N18: Nguyễn Minh Khôi
A19: ADM-PRAC-SPK-008 | B19: Frontend speaking scenario editor | C19: Admin logged in | D19: Open practice → speaking scenarios | E19: Form, publish toggle | F19: Passed | G19: 46127 | H19: Nguyễn Trần Tấn Phát | I19: Passed | J19: 46134 | K19: Nguyễn Minh Khôi | L19: Passed | M19: 46141 | N19: Hoàng Văn Anh Nghĩa

Sheet Admin Users
A2: Feature | B2: Admin User Mgmt
A3: Test requirement | B3: User CRUD, deactivate, role enforcement, frontend
A4: Number of TCs | B4: =COUNTA(A12:A997)
A5: Testing Round | B5: Passed | C5: Failed | D5: Pending | E5: N/A
A6: Round 1 | B6: =COUNTIF($F$12:$F$997,B$5) | C6: =COUNTIF($F$12:$F$997,C$5) | D6: =COUNTIF($F$12:$F$997,D$5) | E6: =COUNTIF($F$12:$F$997,E$5)
A7: Round 2 | B7: =COUNTIF($I$12:$I$997,B$5) | C7: =COUNTIF($I$12:$I$997,C$5) | D7: =COUNTIF($I$12:$I$997,D$5) | E7: =COUNTIF($I$12:$I$997,E$5)
A8: Round 3 | B8: =COUNTIF($L$12:$L$997,B$5) | C8: =COUNTIF($L$12:$L$997,C$5) | D8: =COUNTIF($L$12:$L$997,D$5) | E8: =COUNTIF($L$12:$L$997,E$5)
A10: Test Case ID | B10: Test Case Description | C10: Test Case Procedure | D10: Expected Results | E10: Pre-conditions | F10: Round 1 | G10: Test date | H10: Tester | I10: Round 2 | J10: Test date | K10: Tester | L10: Round 3 | M10: Test date | N10: Tester | O10: Note
A11: Admin
A12: ADM-USR-001 | B12: List users | C12: Admin authenticated | D12: GET `admin/users` | E12: 200, user list with roles, searchable | F12: Passed | G12: 46127 | H12: Hoàng Văn Anh Nghĩa | I12: Passed | J12: 46134 | K12: Nguyễn Nhật Phát | L12: Passed | M12: 46141 | N12: Nguyễn Trần Tấn Phát
A13: ADM-USR-002 | B13: Create user with role | C13: Admin authenticated | D13: POST `admin/users` with email/name/password/role | E13: 201, user created | F13: Passed | G13: 46127 | H13: Nguyễn Nhật Phát | I13: Passed | J13: 46134 | K13: Nguyễn Trần Tấn Phát | L13: Passed | M13: 46141 | N13: Nguyễn Minh Khôi
A14: ADM-USR-004 | B14: Deactivate user | C14: Active user | D14: POST `admin/users/{id}/deactivate` | E14: 200, user cannot login | F14: Passed | G14: 46127 | H14: Nguyễn Trần Tấn Phát | I14: Passed | J14: 46134 | K14: Nguyễn Minh Khôi | L14: Passed | M14: 46141 | N14: Hoàng Văn Anh Nghĩa
A15: ADM-USR-010 | B15: User management is admin-only | C15: Staff user (not admin) | D15: Access admin user routes | E15: 403 | F15: Passed | G15: 46127 | H15: Nguyễn Minh Khôi | I15: Passed | J15: 46134 | K15: Hoàng Văn Anh Nghĩa | L15: Passed | M15: 46141 | N15: Nguyễn Nhật Phát
A16: ADM-USR-011 | B16: Frontend user management page | C16: Admin logged in | D16: Open users page | E16: User table, create/edit form, role selector, deactivate actions | F16: Passed | G16: 46127 | H16: Hoàng Văn Anh Nghĩa | I16: Passed | J16: 46134 | K16: Nguyễn Nhật Phát | L16: Passed | M16: 46141 | N16: Nguyễn Trần Tấn Phát

Sheet Admin Courses
A2: Feature | B2: Admin Course & Promo
A3: Test requirement | B3: Course CRUD, enrollments, bookings, promo, top-up
A4: Number of TCs | B4: =COUNTA(A12:A997)
A5: Testing Round | B5: Passed | C5: Failed | D5: Pending | E5: N/A
A6: Round 1 | B6: =COUNTIF($F$12:$F$997,B$5) | C6: =COUNTIF($F$12:$F$997,C$5) | D6: =COUNTIF($F$12:$F$997,D$5) | E6: =COUNTIF($F$12:$F$997,E$5)
A7: Round 2 | B7: =COUNTIF($I$12:$I$997,B$5) | C7: =COUNTIF($I$12:$I$997,C$5) | D7: =COUNTIF($I$12:$I$997,D$5) | E7: =COUNTIF($I$12:$I$997,E$5)
A8: Round 3 | B8: =COUNTIF($L$12:$L$997,B$5) | C8: =COUNTIF($L$12:$L$997,C$5) | D8: =COUNTIF($L$12:$L$997,D$5) | E8: =COUNTIF($L$12:$L$997,E$5)
A10: Test Case ID | B10: Test Case Description | C10: Test Case Procedure | D10: Expected Results | E10: Pre-conditions | F10: Round 1 | G10: Test date | H10: Tester | I10: Round 2 | J10: Test date | K10: Tester | L10: Round 3 | M10: Test date | N10: Tester | O10: Note
A11: Admin
A12: ADM-CRS-002 | B12: Create course | C12: Admin authenticated | D12: POST `admin/courses` with title/teacher/price/dates | E12: 201 | F12: Passed | G12: 46127 | H12: Nguyễn Nhật Phát | I12: Passed | J12: 46134 | K12: Nguyễn Trần Tấn Phát | L12: Passed | M12: 46141 | N12: Nguyễn Minh Khôi
A13: ADM-CRS-004 | B13: Publish/unpublish course | C13: Course exists | D13: POST publish/unpublish | E13: Status changes | F13: Passed | G13: 46127 | H13: Nguyễn Trần Tấn Phát | I13: Passed | J13: 46134 | K13: Nguyễn Minh Khôi | L13: Passed | M13: 46141 | N13: Hoàng Văn Anh Nghĩa
A14: ADM-CRS-006 | B14: Manage enrollments | C14: Course exists | D14: GET/POST/DELETE enrollments | E14: Learners added/removed, commitment overridable | F14: Passed | G14: 46127 | H14: Nguyễn Minh Khôi | I14: Passed | J14: 46134 | K14: Hoàng Văn Anh Nghĩa | L14: Passed | M14: 46141 | N14: Nguyễn Nhật Phát
A15: ADM-CRS-008 | B15: Manage bookings (meet_url + cancel/refund) | C15: Bookings exist | D15: PATCH meet_url, POST cancel with refund | E15: Refund processed | F15: Passed | G15: 46127 | H15: Hoàng Văn Anh Nghĩa | I15: Passed | J15: 46134 | K15: Nguyễn Nhật Phát | L15: Passed | M15: 46141 | N15: Nguyễn Trần Tấn Phát
A16: ADM-CRS-009 | B16: Frontend course detail with tabs | C16: Admin logged in | D16: Open course detail | E16: Schedule items, enrollments, slots, bookings tabs | F16: Passed | G16: 46127 | H16: Nguyễn Nhật Phát | I16: Passed | J16: 46134 | K16: Nguyễn Trần Tấn Phát | L16: Passed | M16: 46141 | N16: Nguyễn Minh Khôi
A17: ADM-PROMO-001 | B17: List promo codes | C17: Admin authenticated | D17: GET `admin/promo-codes` | E17: 200, promo list with usage/status | F17: Passed | G17: 46127 | H17: Nguyễn Trần Tấn Phát | I17: Passed | J17: 46134 | K17: Nguyễn Minh Khôi | L17: Passed | M17: 46141 | N17: Hoàng Văn Anh Nghĩa
A18: ADM-PROMO-002 | B18: Create promo code | C18: Admin authenticated | D18: POST with code/coins/valid_until/usage_limit | E18: 201 | F18: Passed | G18: 46127 | H18: Nguyễn Minh Khôi | I18: Passed | J18: 46134 | K18: Hoàng Văn Anh Nghĩa | L18: Passed | M18: 46141 | N18: Nguyễn Nhật Phát
A19: ADM-PROMO-005 | B19: Frontend promo code page | C19: Admin logged in | D19: Open promo section | E19: Promo list, create/edit form | F19: Passed | G19: 46127 | H19: Hoàng Văn Anh Nghĩa | I19: Passed | J19: 46134 | K19: Nguyễn Nhật Phát | L19: Passed | M19: 46141 | N19: Nguyễn Trần Tấn Phát
A20: ADM-TOPUP-001 | B20: List top-up packages | C20: Admin authenticated | D20: GET `admin/topup-packages` | E20: 200, package list with status | F20: Passed | G20: 46127 | H20: Nguyễn Nhật Phát | I20: Passed | J20: 46134 | K20: Nguyễn Trần Tấn Phát | L20: Passed | M20: 46141 | N20: Nguyễn Minh Khôi
A21: ADM-TOPUP-002 | B21: Create top-up package | C21: Admin authenticated | D21: POST with label/price/coins/bonus/order | E21: 201 | F21: Passed | G21: 46127 | H21: Nguyễn Trần Tấn Phát | I21: Passed | J21: 46134 | K21: Nguyễn Minh Khôi | L21: Passed | M21: 46141 | N21: Hoàng Văn Anh Nghĩa
A22: ADM-TOPUP-005 | B22: Frontend top-up packages page | C22: Admin logged in | D22: Open top-up packages | E22: List, create/edit form, activate/deactivate | F22: Passed | G22: 46127 | H22: Nguyễn Minh Khôi | I22: Passed | J22: 46134 | K22: Hoàng Văn Anh Nghĩa | L22: Passed | M22: 46141 | N22: Nguyễn Nhật Phát

Sheet Teacher
A2: Feature | B2: Teacher
A3: Test requirement | B3: Dashboard, schedule, bookings, leave requests
A4: Number of TCs | B4: =COUNTA(A12:A997)
A5: Testing Round | B5: Passed | C5: Failed | D5: Pending | E5: N/A
A6: Round 1 | B6: =COUNTIF($F$12:$F$997,B$5) | C6: =COUNTIF($F$12:$F$997,C$5) | D6: =COUNTIF($F$12:$F$997,D$5) | E6: =COUNTIF($F$12:$F$997,E$5)
A7: Round 2 | B7: =COUNTIF($I$12:$I$997,B$5) | C7: =COUNTIF($I$12:$I$997,C$5) | D7: =COUNTIF($I$12:$I$997,D$5) | E7: =COUNTIF($I$12:$I$997,E$5)
A8: Round 3 | B8: =COUNTIF($L$12:$L$997,B$5) | C8: =COUNTIF($L$12:$L$997,C$5) | D8: =COUNTIF($L$12:$L$997,D$5) | E8: =COUNTIF($L$12:$L$997,E$5)
A10: Test Case ID | B10: Test Case Description | C10: Test Case Procedure | D10: Expected Results | E10: Pre-conditions | F10: Round 1 | G10: Test date | H10: Tester | I10: Round 2 | J10: Test date | K10: Tester | L10: Round 3 | M10: Test date | N10: Tester | O10: Note
A11: Teacher
A12: TCH-DASH-001 | B12: Teacher dashboard returns stats | C12: Teacher authenticated with assigned courses | D12: GET `teacher/dashboard` | E12: 200, dashboard data with course stats | F12: Passed | G12: 46127 | H12: Nguyễn Trần Tấn Phát | I12: Passed | J12: 46134 | K12: Nguyễn Minh Khôi | L12: Passed | M12: 46141 | N12: Hoàng Văn Anh Nghĩa
A13: TCH-DASH-002 | B13: Teacher cannot access admin-only routes | C13: Teacher role (not admin) | D13: GET `admin/system-config` | E13: 403 | F13: Passed | G13: 46127 | H13: Nguyễn Minh Khôi | I13: Passed | J13: 46134 | K13: Hoàng Văn Anh Nghĩa | L13: Passed | M13: 46141 | N13: Nguyễn Nhật Phát
A14: TCH-SCH-001 | B14: List schedule items | C14: Teacher authenticated, courses assigned | D14: GET `teacher/schedule-items` | E14: 200, schedule list with course/date/time | F14: Passed | G14: 46127 | H14: Hoàng Văn Anh Nghĩa | I14: Passed | J14: 46134 | K14: Nguyễn Nhật Phát | L14: Passed | M14: 46141 | N14: Nguyễn Trần Tấn Phát
A15: TCH-SCH-002 | B15: Frontend teacher schedule calendar | C15: Teacher logged in | D15: Open teacher schedule page | E15: Calendar with DayCell, EventCard, EventDetailModal | F15: Passed | G15: 46127 | H15: Nguyễn Nhật Phát | I15: Passed | J15: 46134 | K15: Nguyễn Trần Tấn Phát | L15: Passed | M15: 46141 | N15: Nguyễn Minh Khôi
A16: TCH-BK-001 | B16: List teacher bookings | C16: Bookings exist | D16: GET `teacher/bookings` | E16: 200, booking list with learner, status | F16: Passed | G16: 46127 | H16: Nguyễn Trần Tấn Phát | I16: Passed | J16: 46134 | K16: Nguyễn Minh Khôi | L16: Passed | M16: 46141 | N16: Hoàng Văn Anh Nghĩa
A17: TCH-LEAVE-002 | B17: Create leave request | C17: Teacher authenticated | D17: POST `teacher/leave-requests` with date/reason | E17: 201, leave request created, status pending | F17: Passed | G17: 46127 | H17: Nguyễn Minh Khôi | I17: Passed | J17: 46134 | K17: Hoàng Văn Anh Nghĩa | L17: Passed | M17: 46141 | N17: Nguyễn Nhật Phát
A18: TCH-LEAVE-003 | B18: Staff approves leave request | C18: Staff authenticated, pending leave | D18: PATCH `admin/leave-requests/{id}` with approved | E18: 200, leave approved | F18: Passed | G18: 46127 | H18: Hoàng Văn Anh Nghĩa | I18: Passed | J18: 46134 | K18: Nguyễn Nhật Phát | L18: Passed | M18: 46141 | N18: Nguyễn Trần Tấn Phát

Sheet Grading AI
A2: Feature | B2: Grading & AI
A3: Test requirement | B3: Result lookup, SSE, scoring formulas, pipeline
A4: Number of TCs | B4: =COUNTA(A12:A997)
A5: Testing Round | B5: Passed | C5: Failed | D5: Pending | E5: N/A
A6: Round 1 | B6: =COUNTIF($F$12:$F$997,B$5) | C6: =COUNTIF($F$12:$F$997,C$5) | D6: =COUNTIF($F$12:$F$997,D$5) | E6: =COUNTIF($F$12:$F$997,E$5)
A7: Round 2 | B7: =COUNTIF($I$12:$I$997,B$5) | C7: =COUNTIF($I$12:$I$997,C$5) | D7: =COUNTIF($I$12:$I$997,D$5) | E7: =COUNTIF($I$12:$I$997,E$5)
A8: Round 3 | B8: =COUNTIF($L$12:$L$997,B$5) | C8: =COUNTIF($L$12:$L$997,C$5) | D8: =COUNTIF($L$12:$L$997,D$5) | E8: =COUNTIF($L$12:$L$997,E$5)
A10: Test Case ID | B10: Test Case Description | C10: Test Case Procedure | D10: Expected Results | E10: Pre-conditions | F10: Round 1 | G10: Test date | H10: Tester | I10: Round 2 | J10: Test date | K10: Tester | L10: Round 3 | M10: Test date | N10: Tester | O10: Note
A11: Backend
A12: GRD-WF-003 | B12: Writing result lookup by submission type | C12: Graded writing submission exists | D12: GET `grading/writing/{submissionType}/{submissionId}` | E12: 200, writing result with band, rubric scores, feedback | F12: Passed | G12: 46127 | H12: Nguyễn Minh Khôi | I12: Passed | J12: 46134 | K12: Hoàng Văn Anh Nghĩa | L12: Passed | M12: 46141 | N12: Nguyễn Nhật Phát
A13: GRD-WF-004 | B13: Speaking result lookup by submission type | C13: Graded speaking submission exists | D13: GET `grading/speaking/{submissionType}/{submissionId}` | E13: 200, speaking result with band, rubric scores, transcript | F13: Passed | G13: 46127 | H13: Hoàng Văn Anh Nghĩa | I13: Passed | J13: 46134 | K13: Nguyễn Nhật Phát | L13: Passed | M13: 46141 | N13: Nguyễn Trần Tấn Phát
A14: GRD-WF-005 | B14: Grading SSE stream emits progress/scores/feedback | C14: Active grading job | D14: GET `grading-jobs/{id}/stream` | E14: SSE events: progress, scores, feedback, done/completed | F14: Passed | G14: 46127 | H14: Nguyễn Nhật Phát | I14: Passed | J14: 46134 | K14: Nguyễn Trần Tấn Phát | L14: Passed | M14: 46141 | N14: Nguyễn Minh Khôi
A15: GRD-WF-006 | B15: FeedbackCompleted event fires after grading | C15: Grading completes | D15: Grading pipeline finishes | E15: Event dispatched, notification sent | F15: Passed | G15: 46127 | H15: Nguyễn Trần Tấn Phát | I15: Passed | J15: 46134 | K15: Nguyễn Minh Khôi | L15: Passed | M15: 46141 | N15: Hoàng Văn Anh Nghĩa
A16: GRD-WRI-001 | B16: Writing scoring formula with valid rubric parameters | C16: Valid rubric data | D16: Run scoring formula | E16: Deterministic score based on rubric weights and evidence | F16: Passed | G16: 46127 | H16: Nguyễn Minh Khôi | I16: Passed | J16: 46134 | K16: Hoàng Văn Anh Nghĩa | L16: Passed | M16: 46141 | N16: Nguyễn Nhật Phát
A17: GRD-WRI-005 | B17: Writing validation: VSTEP requirements | C17: Writing submission | D17: Validate submission against VSTEP criteria | E17: Valid/invalid based on task type, word count, content | F17: Passed | G17: 46127 | H17: Hoàng Văn Anh Nghĩa | I17: Passed | J17: 46134 | K17: Nguyễn Nhật Phát | L17: Passed | M17: 46141 | N17: Nguyễn Trần Tấn Phát
A18: GRD-SPK-001 | B18: Speaking scoring formula with rubric parameters | C18: Valid rubric data | D18: Run scoring formula | E18: Band score based on pronunciation, fluency, grammar, vocabulary | F18: Passed | G18: 46127 | H18: Nguyễn Nhật Phát | I18: Passed | J18: 46134 | K18: Nguyễn Trần Tấn Phát | L18: Passed | M18: 46141 | N18: Nguyễn Minh Khôi
A19: GRD-SPK-002 | B19: Conversation turn handling | C19: User audio and text | D19: Process conversation turn | E19: Content relevance, task fulfillment assessed | F19: Passed | G19: 46127 | H19: Nguyễn Trần Tấn Phát | I19: Passed | J19: 46134 | K19: Nguyễn Minh Khôi | L19: Passed | M19: 46141 | N19: Hoàng Văn Anh Nghĩa
A20: GRD-AI-001 | B20: LLM grading service handles request/response | C20: Grading request | D20: Send to LLM, receive response | E20: Correct wire format, parsed grading result | F20: Passed | G20: 46127 | H20: Nguyễn Minh Khôi | I20: Passed | J20: 46134 | K20: Hoàng Văn Anh Nghĩa | L20: Passed | M20: 46141 | N20: Nguyễn Nhật Phát
A21: GRD-AI-005 | B21: Grading pipeline end-to-end (test) | C21: Full grading pipeline test | D21: Submit writing/speaking, observe pipeline | E21: Grading job created, processing, result persisted, event fired | F21: Passed | G21: 46127 | H21: Hoàng Văn Anh Nghĩa | I21: Passed | J21: 46134 | K21: Nguyễn Nhật Phát | L21: Passed | M21: 46141 | N21: Nguyễn Trần Tấn Phát

Sheet System
A2: Feature | B2: System Integration
A3: Test requirement | B3: Role hierarchy, health, config, cross-module
A4: Number of TCs | B4: =COUNTA(A12:A997)
A5: Testing Round | B5: Passed | C5: Failed | D5: Pending | E5: N/A
A6: Round 1 | B6: =COUNTIF($F$12:$F$997,B$5) | C6: =COUNTIF($F$12:$F$997,C$5) | D6: =COUNTIF($F$12:$F$997,D$5) | E6: =COUNTIF($F$12:$F$997,E$5)
A7: Round 2 | B7: =COUNTIF($I$12:$I$997,B$5) | C7: =COUNTIF($I$12:$I$997,C$5) | D7: =COUNTIF($I$12:$I$997,D$5) | E7: =COUNTIF($I$12:$I$997,E$5)
A8: Round 3 | B8: =COUNTIF($L$12:$L$997,B$5) | C8: =COUNTIF($L$12:$L$997,C$5) | D8: =COUNTIF($L$12:$L$997,D$5) | E8: =COUNTIF($L$12:$L$997,E$5)
A10: Test Case ID | B10: Test Case Description | C10: Test Case Procedure | D10: Expected Results | E10: Pre-conditions | F10: Round 1 | G10: Test date | H10: Tester | I10: Round 2 | J10: Test date | K10: Tester | L10: Round 3 | M10: Test date | N10: Tester | O10: Note
A11: Backend
A12: SYS-AUTH-001 | B12: Authenticated learner cannot access admin routes | C12: Learner token | D12: GET `admin/stats` | E12: 403 | F12: Passed | G12: 46127 | H12: Hoàng Văn Anh Nghĩa | I12: Passed | J12: 46134 | K12: Nguyễn Nhật Phát | L12: Passed | M12: 46141 | N12: Nguyễn Trần Tấn Phát
A13: SYS-AUTH-003 | B13: Staff cannot access admin-only routes (system config, users, promo) | C13: Staff token (not admin) | D13: GET `admin/system-config` | E13: 403 | F13: Passed | G13: 46127 | H13: Nguyễn Nhật Phát | I13: Passed | J13: 46134 | K13: Nguyễn Trần Tấn Phát | L13: Passed | M13: 46141 | N13: Nguyễn Minh Khôi
A14: SYS-AUTH-004 | B14: Teacher can access teacher routes | C14: Teacher token | D14: GET `teacher/dashboard` | E14: 200 | F14: Passed | G14: 46127 | H14: Nguyễn Trần Tấn Phát | I14: Passed | J14: 46134 | K14: Nguyễn Minh Khôi | L14: Passed | M14: 46141 | N14: Hoàng Văn Anh Nghĩa
A15: SYS-AUTH-006 | B15: Unauthenticated request rejected for protected routes | C15: No token | D15: GET any protected endpoint | E15: 401 | F15: Passed | G15: 46127 | H15: Nguyễn Minh Khôi | I15: Passed | J15: 46134 | K15: Hoàng Văn Anh Nghĩa | L15: Passed | M15: 46141 | N15: Nguyễn Nhật Phát
A16: SYS-INT-001 | B16: Exam submission triggers streak update | C16: Learner submits full-test exam | D16: Submit exam, check streak | E16: Streak updated if first full-test today | F16: Passed | G16: 46127 | H16: Hoàng Văn Anh Nghĩa | I16: Passed | J16: 46134 | K16: Nguyễn Nhật Phát | L16: Passed | M16: 46141 | N16: Nguyễn Trần Tấn Phát
A17: SYS-INT-002 | B17: Grading completion triggers notification | C17: Writing/speaking graded | D17: Grading completes | E17: Notification created for learner | F17: Passed | G17: 46127 | H17: Nguyễn Nhật Phát | I17: Passed | J17: 46134 | K17: Nguyễn Trần Tấn Phát | L17: Passed | M17: 46141 | N17: Nguyễn Minh Khôi
A18: SYS-INT-003 | B18: Top-up completion triggers notification | C18: Payment callback confirms top-up | D18: Top-up confirmed | E18: Notification created, wallet balance updated in UI | F18: Passed | G18: 46127 | H18: Nguyễn Trần Tấn Phát | I18: Passed | J18: 46134 | K18: Nguyễn Minh Khôi | L18: Passed | M18: 46141 | N18: Hoàng Văn Anh Nghĩa
A19: SYS-HLTH-001 | B19: Health endpoint returns OK | C19: Backend running, DB connected | D19: GET `health` | E19: 200, status ok | F19: Passed | G19: 46127 | H19: Nguyễn Minh Khôi | I19: Passed | J19: 46134 | K19: Hoàng Văn Anh Nghĩa | L19: Passed | M19: 46141 | N19: Nguyễn Nhật Phát
A20: SYS-HLTH-002 | B20: Config endpoint returns app config | C20: Backend running | D20: GET `config` | E20: 200, pricing, exam config, chart config values returned | F20: Passed | G20: 46127 | H20: Hoàng Văn Anh Nghĩa | I20: Passed | J20: 46134 | K20: Nguyễn Nhật Phát | L20: Passed | M20: 46141 | N20: Nguyễn Trần Tấn Phát
A21: SYS-PAY-001 | B21: Payment callback endpoint is public | C21: No auth required | D21: POST `payment/callback/{provider}` | E21: Processes without auth, provider-specific data | F21: Passed | G21: 46127 | H21: Nguyễn Nhật Phát | I21: Passed | J21: 46134 | K21: Nguyễn Trần Tấn Phát | L21: Passed | M21: 46141 | N21: Nguyễn Minh Khôi

Sheet Non-functional
A2: Feature | B2: Non-functional
A3: Test requirement | B3: Security, performance, compatibility, usability, reliability
A4: Number of TCs | B4: =COUNTA(A12:A997)
A5: Testing Round | B5: Passed | C5: Failed | D5: Pending | E5: N/A
A6: Round 1 | B6: =COUNTIF($F$12:$F$997,B$5) | C6: =COUNTIF($F$12:$F$997,C$5) | D6: =COUNTIF($F$12:$F$997,D$5) | E6: =COUNTIF($F$12:$F$997,E$5)
A7: Round 2 | B7: =COUNTIF($I$12:$I$997,B$5) | C7: =COUNTIF($I$12:$I$997,C$5) | D7: =COUNTIF($I$12:$I$997,D$5) | E7: =COUNTIF($I$12:$I$997,E$5)
A8: Round 3 | B8: =COUNTIF($L$12:$L$997,B$5) | C8: =COUNTIF($L$12:$L$997,C$5) | D8: =COUNTIF($L$12:$L$997,D$5) | E8: =COUNTIF($L$12:$L$997,E$5)
A10: Test Case ID | B10: Test Case Description | C10: Test Case Procedure | D10: Expected Results | E10: Pre-conditions | F10: Round 1 | G10: Test date | H10: Tester | I10: Round 2 | J10: Test date | K10: Tester | L10: Round 3 | M10: Test date | N10: Tester | O10: Note
A11: System
A12: NFT-SEC-001 | B12: Expired token rejected on all protected endpoints | C12: Expired access token | D12: Call protected endpoint | E12: 401 Unauthorized | F12: Passed | G12: 46127 | H12: Nguyễn Nhật Phát | I12: Passed | J12: 46134 | K12: Nguyễn Trần Tấn Phát | L12: Passed | M12: 46141 | N12: Nguyễn Minh Khôi
A13: NFT-SEC-003 | B13: Learner cannot access admin/staff API | C13: Learner token | D13: Call `admin/*` endpoints | E13: 403 | F13: Passed | G13: 46127 | H13: Nguyễn Trần Tấn Phát | I13: Passed | J13: 46134 | K13: Nguyễn Minh Khôi | L13: Passed | M13: 46141 | N13: Hoàng Văn Anh Nghĩa
A14: NFT-SEC-005 | B14: User cannot access other user's profile | C14: Learner token for user A | D14: PATCH `profiles/{userB_profile_id}` | E14: 403 or 404 | F14: Passed | G14: 46127 | H14: Nguyễn Minh Khôi | I14: Passed | J14: 46134 | K14: Hoàng Văn Anh Nghĩa | L14: Passed | M14: 46141 | N14: Nguyễn Nhật Phát
A15: NFT-SEC-007 | B15: Password not exposed in API responses | C15: Login response | D15: Inspect response body | E15: No password hash or raw password returned | F15: Passed | G15: 46127 | H15: Hoàng Văn Anh Nghĩa | I15: Passed | J15: 46134 | K15: Nguyễn Nhật Phát | L15: Passed | M15: 46141 | N15: Nguyễn Trần Tấn Phát
A16: NFT-SEC-011 | B16: XSS prevented | C16: Writing/submission endpoints | D16: Input script tags in writing answer | E16: Script tags not rendered as HTML in result | F16: Passed | G16: 46127 | H16: Nguyễn Nhật Phát | I16: Passed | J16: 46134 | K16: Nguyễn Trần Tấn Phát | L16: Passed | M16: 46141 | N16: Nguyễn Minh Khôi
A17: NFT-PERF-001 | B17: AI grading response/job accepted within 3 seconds | C17: Writing/speaking submission | D17: Submit and measure time to grading job creation | E17: Job created within 3 seconds of submission request | F17: Passed | G17: 46127 | H17: Nguyễn Trần Tấn Phát | I17: Passed | J17: 46134 | K17: Nguyễn Minh Khôi | L17: Passed | M17: 46141 | N17: Hoàng Văn Anh Nghĩa
A18: NFT-PERF-002 | B18: API responses under 2 seconds for common endpoints | C18: Backend running, cached config | D18: Request exams, profile, dashboard endpoints | E18: Response time under 2 seconds | F18: Passed | G18: 46127 | H18: Nguyễn Minh Khôi | I18: Passed | J18: 46134 | K18: Hoàng Văn Anh Nghĩa | L18: Passed | M18: 46141 | N18: Nguyễn Nhật Phát
A19: NFT-COMP-001 | B19: Learner web works on Chrome latest | C19: Chrome browser | D19: Open login, register, dashboard, exam room | E19: All pages render, forms work | F19: Passed | G19: 46127 | H19: Hoàng Văn Anh Nghĩa | I19: Passed | J19: 46134 | K19: Nguyễn Nhật Phát | L19: Passed | M19: 46141 | N19: Nguyễn Trần Tấn Phát
A20: NFT-USE-003 | B20: Exam room exit confirmation protects accidental exit | C20: Active exam | D20: Click exit during exam | E20: Confirmation dialog with countdown before exiting | F20: Passed | G20: 46127 | H20: Nguyễn Nhật Phát | I20: Passed | J20: 46134 | K20: Nguyễn Trần Tấn Phát | L20: Passed | M20: 46141 | N20: Nguyễn Minh Khôi
A21: NFT-USE-005 | B21: Empty states are informative | C21: Empty list pages | D21: Open empty vocab, grammar, submitted exams | E21: Informative message and CTA visible | F21: Passed | G21: 46127 | H21: Nguyễn Trần Tấn Phát | I21: Passed | J21: 46134 | K21: Nguyễn Minh Khôi | L21: Passed | M21: 46141 | N21: Hoàng Văn Anh Nghĩa
A22: NFT-REL-001 | B22: Data consistency after exam submit | C22: Submit exam | D22: Refresh page, check result via API | E22: Same score and details returned consistently | F22: Passed | G22: 46127 | H22: Nguyễn Minh Khôi | I22: Passed | J22: 46134 | K22: Hoàng Văn Anh Nghĩa | L22: Passed | M22: 46141 | N22: Nguyễn Nhật Phát
A23: NFT-REL-002 | B23: Draft save survives page crash simulation | C23: Active exam with answers | D23: Close tab during exam, reopen | E23: Draft restored from last autosave | F23: Passed | G23: 46127 | H23: Hoàng Văn Anh Nghĩa | I23: Passed | J23: 46134 | K23: Nguyễn Nhật Phát | L23: Passed | M23: 46141 | N23: Nguyễn Trần Tấn Phát
